[{"id":"d087fa29.08fdc8","type":"tab","label":"NCID Client","disabled":false,"info":""},{"id":"9c834b39.564c48","type":"tab","label":"Dashboard","disabled":false,"info":""},{"id":"19e925d9.c9f0ba","type":"tab","label":"Logs","disabled":false,"info":""},{"id":"8cb3e04d.83f54","type":"tab","label":"Lighting Flows","disabled":false,"info":""},{"id":"77549aa8.a94944","type":"tab","label":"Nat Repeaters","disabled":false,"info":""},{"id":"32eaa2f3.09c81e","type":"tab","label":"Weather","disabled":false,"info":""},{"id":"d862700a.a9435","type":"tab","label":"Nest","disabled":false,"info":""},{"id":"5e8c75af.480b0c","type":"tab","label":"NeoPixel Hallway","disabled":false,"info":""},{"id":"99f288e8.63d4c8","type":"tab","label":"NeoPixel Amelia","disabled":false,"info":""},{"id":"6895dc3b.267224","type":"subflow","name":"SmoothSample","info":"","category":"","in":[{"x":80,"y":40,"wires":[{"id":"2ae5f888.fbebd8"}]}],"out":[{"x":560,"y":40,"wires":[{"id":"2ae5f888.fbebd8","port":0}]}],"env":[]},{"id":"e2eaf260.27fa1","type":"mqtt-broker","broker":"localhost","port":"1883","clientid":"","usetls":false,"compatmode":true,"keepalive":"60","cleansession":true,"birthTopic":"","birthQos":"0","birthPayload":"","willTopic":"","willQos":"0","willPayload":""},{"id":"2f831b66.758144","type":"ui_tab","name":"Home","icon":"dashboard","order":1},{"id":"2a1f0af5.2418f6","type":"ui_base","theme":{"name":"theme-dark","lightTheme":{"default":"#0094CE","baseColor":"#3f8f86","baseFont":"-apple-system,BlinkMacSystemFont,Segoe UI,Roboto,Oxygen-Sans,Ubuntu,Cantarell,Helvetica Neue,sans-serif","edited":true,"reset":false},"darkTheme":{"default":"#097479","baseColor":"#097479","baseFont":"Tahoma,Geneva,sans-serif","edited":true,"reset":false},"customTheme":{"name":"Untitled Theme 1","default":"#4B7930","baseColor":"#4B7930","baseFont":"Tahoma,Geneva,sans-serif","reset":false},"themeState":{"base-color":{"default":"#097479","value":"#097479","edited":true},"page-titlebar-backgroundColor":{"value":"#097479","edited":false},"page-backgroundColor":{"value":"#111111","edited":false},"page-sidebar-backgroundColor":{"value":"#333333","edited":false},"group-textColor":{"value":"#0eb8c0","edited":false},"group-borderColor":{"value":"#555555","edited":false},"group-backgroundColor":{"value":"#333333","edited":false},"widget-textColor":{"value":"#eeeeee","edited":false},"widget-backgroundColor":{"value":"#097479","edited":false},"widget-borderColor":{"value":"#333333","edited":false},"base-font":{"value":"Tahoma,Geneva,sans-serif"}},"angularTheme":{"primary":"indigo","accents":"blue","warn":"red","background":"grey","palette":"dark"}},"site":{"name":"Node-RED Dashboard","hideToolbar":"false","allowSwipe":"false","dateFormat":"DD/MM/YYYY","sizes":{"sx":52,"sy":48,"gx":6,"gy":6,"cx":6,"cy":6,"px":0,"py":0},"allowTempTheme":"true","lockMenu":"false"}},{"id":"b6867966.7e4de8","type":"ui_group","name":"Status","tab":"2f831b66.758144","order":1,"disp":false,"width":"6","collapse":false},{"id":"824cf83e.293e98","type":"ui_group","name":"MQTT","tab":"84c5bc18.9bef7","order":3,"disp":true,"width":"16","collapse":true},{"id":"a5ed876a.3e1978","type":"ui_group","name":"Access Point","tab":"84c5bc18.9bef7","order":1,"disp":true,"width":"8","collapse":false},{"id":"ed92ea3f.c10ff8","type":"ui_group","name":"HomeAP","tab":"84c5bc18.9bef7","order":2,"disp":true,"width":"8","collapse":false},{"id":"9a6c950b.59f2e8","type":"ui_group","name":"Caller ID","tab":"2f831b66.758144","order":5,"disp":false,"width":"6","collapse":false},{"id":"84c5bc18.9bef7","type":"ui_tab","name":"Logs","icon":"subject","order":2},{"id":"9faad522.25f398","type":"ui_group","name":"Monitor","tab":"2f831b66.758144","order":4,"disp":false,"width":"18","collapse":false},{"id":"7c2f62b7.5eac4c","type":"ui_group","name":"ESP Clock","tab":"84c5bc18.9bef7","order":4,"disp":false,"width":"4","collapse":false},{"id":"f16fdd32.15974","type":"darksky-credentials","key_identifier":"Grak"},{"id":"5a430243.08a5cc","type":"ui_group","name":"NeoPixel Hallway","tab":"7e866fff.b92d7","order":5,"disp":true,"width":"6","collapse":false},{"id":"7e866fff.b92d7","type":"ui_tab","name":"NeoPixel Hallway","icon":"dashboard","order":3,"disabled":false,"hidden":false},{"id":"fd4d4e0b.1ff3a","type":"ui_tab","name":"NeoPixel Amelia","icon":"dashboard","order":4,"disabled":false,"hidden":false},{"id":"85002a37.c1c1f8","type":"ui_group","name":"NeoPixel Amelia","tab":"fd4d4e0b.1ff3a","order":1,"disp":true,"width":"6","collapse":false},{"id":"2e3fadb2.11fcb2","type":"ui_tab","name":"NeoPixel Phoebe","icon":"dashboard","order":5,"disabled":false,"hidden":false},{"id":"b0edfcc5.15995","type":"ui_group","name":"NeoPixel Phoebe","tab":"2e3fadb2.11fcb2","order":1,"disp":true,"width":"6","collapse":false},{"id":"a3d8fcdc.db27f","type":"ui_group","name":"Nest","tab":"1d8f4f5.c2b2ab1","order":1,"disp":true,"width":"4","collapse":false},{"id":"1d8f4f5.c2b2ab1","type":"ui_tab","name":"Nest Thermostat sample","icon":"dashboard","order":3},{"id":"bbca3c6e.ed129","type":"mqtt out","z":"8cb3e04d.83f54","name":"","topic":"cmnd/LightLR/POWER1","qos":"1","retain":"","broker":"e2eaf260.27fa1","x":830,"y":180,"wires":[]},{"id":"a506193e.0672f8","type":"mqtt in","z":"9c834b39.564c48","name":"","topic":"alarm/current/state","qos":"0","broker":"e2eaf260.27fa1","x":130,"y":900,"wires":[["410fa8da.308d18","46264e44.91c3f"]]},{"id":"af2f5fdc.7e9d","type":"mqtt in","z":"9c834b39.564c48","name":"","topic":"alarm/heartbeat","qos":"0","datatype":"auto","broker":"e2eaf260.27fa1","x":100,"y":660,"wires":[["a9cf862f.9cdb78","7ef050e4.9dd9","8e65920.eb0a97"]]},{"id":"9ba7c523.816628","type":"ui_text","z":"9c834b39.564c48","group":"b6867966.7e4de8","order":3,"width":"4","height":"1","name":"","label":"Up Time","format":"{{msg.payload}}","layout":"col-center","x":720,"y":600,"wires":[]},{"id":"14d1c109.ff482f","type":"mqtt in","z":"9c834b39.564c48","name":"","topic":"alarm/rfid/card","qos":"0","broker":"e2eaf260.27fa1","x":122.9999771118164,"y":1413.9999923706055,"wires":[["46c2f02b.4dc23"]]},{"id":"24212092.33eac","type":"mqtt in","z":"9c834b39.564c48","name":"","topic":"alarm/status/env","qos":"0","broker":"e2eaf260.27fa1","x":120,"y":1020,"wires":[["6931407b.72b5b"]]},{"id":"410fa8da.308d18","type":"ui_text","z":"9c834b39.564c48","group":"b6867966.7e4de8","order":1,"width":"2","height":"1","name":"Alarm State","label":"Alarm State","format":"{{msg.payload}}","layout":"row-center","x":730,"y":900,"wires":[]},{"id":"55ef4705.9df718","type":"e-mail","z":"9c834b39.564c48","server":"smtp.gmail.com","port":"465","secure":true,"name":"graham.knight@lastdayofmay.co.uk","dname":"","x":860,"y":760,"wires":[]},{"id":"1b3de2b.a4c341d","type":"function","z":"9c834b39.564c48","name":"timestamp to time","func":"date = new Date(msg.payload.UpTime * 1000);\n\n//msg.payload = date.toTimeString().split(' ')[0];\n\nvar msecPerMinute = 1000 * 60;  \nvar msecPerHour = msecPerMinute * 60;  \nvar msecPerDay = msecPerHour * 24;  \nvar interval = msg.payload.UpTime * 1000;\n\nvar days = Math.floor(interval / msecPerDay );  \ninterval = interval - (days * msecPerDay );  \n\n// Calculate the hours, minutes, and seconds.  \nvar hours = Math.floor(interval / msecPerHour );  \ninterval = interval - (hours * msecPerHour );  \n\nvar minutes = Math.floor(interval / msecPerMinute );  \ninterval = interval - (minutes * msecPerMinute );  \n\nvar seconds = Math.floor(interval / 1000 );  \n\nmsg.payload = util.format(\"%d days %d:%d:%d\", days, hours, minutes, seconds);\n//msg.payload = days + \" days \" + hours + \":\" + minutes + \":\" + seconds;\n\nreturn msg;","outputs":1,"noerr":0,"x":430,"y":600,"wires":[["9ba7c523.816628"]]},{"id":"6931407b.72b5b","type":"json","z":"9c834b39.564c48","name":"","pretty":false,"x":350,"y":1020,"wires":[["eab70576.fc6078"]]},{"id":"cb9d5def.5c5d6","type":"mqtt in","z":"8cb3e04d.83f54","name":"","topic":"alarm/sensor/pirHW","qos":"0","broker":"e2eaf260.27fa1","x":130,"y":440,"wires":[["9f874a74.cde518"]]},{"id":"a7ecaa44.bb9b08","type":"trigger","z":"8cb3e04d.83f54","name":"","op1":"ON","op2":"OFF","op1type":"str","op2type":"str","duration":"5","extend":true,"units":"min","reset":"","outputs":1,"x":510,"y":440,"wires":[["8a9d74a1.e7d228"]]},{"id":"25d04dd.572dbb2","type":"mqtt in","z":"8cb3e04d.83f54","name":"","topic":"alarm/sensor/door","qos":"0","broker":"e2eaf260.27fa1","x":130,"y":620,"wires":[["9f874a74.cde518"]]},{"id":"9f874a74.cde518","type":"switch","z":"8cb3e04d.83f54","name":"","property":"payload","propertyType":"msg","rules":[{"t":"eq","v":"T","vt":"str"}],"checkall":"true","outputs":1,"x":190,"y":540,"wires":[["62bf7467.07053c"]]},{"id":"f84ac2cb.293a9","type":"comment","z":"8cb3e04d.83f54","name":"Detects entry and hallway events - turns light on if its dark","info":"","x":250,"y":400,"wires":[]},{"id":"46264e44.91c3f","type":"function","z":"9c834b39.564c48","name":"If Triggered message","func":"var dt = new Date();    // get the current date and time\n\n// edge detect a state change\nif( context.get(\"lastState\") == msg.payload)\n    return null;\n    \ncontext.set(\"lastState\", msg.payload);\n\n// if a TRIGGERED event\nif( msg.payload == \"TR\")\n{\n    msg.topic = \"Alarm Triggered.\";\n    msg.payload = dt.toDateString() + \" \" + dt.toTimeString();\n    return msg;\n}\n\nif( msg.payload == \"ARM\")\n{\n    msg.topic = \"Alarm Set.\"\n    msg.payload = dt.toDateString() + \" \" + dt.toTimeString();\n    return msg;\n}\n\nif( msg.payload == \"DIS\")\n{\n    msg.topic = \"Alarm Disarmed.\";\n    msg.payload = dt.toDateString() + \" \" + dt.toTimeString();\n    return msg;\n}\n\n\nreturn null;","outputs":1,"noerr":0,"x":540,"y":840,"wires":[["55ef4705.9df718"]]},{"id":"a9cf862f.9cdb78","type":"trigger","z":"9c834b39.564c48","name":"","op1":"","op2":"NO ALARM","op1type":"nul","op2type":"str","duration":"20","extend":true,"units":"s","reset":"","bytopic":"all","outputs":1,"x":370,"y":660,"wires":[["9ba7c523.816628","7ef050e4.9dd9"]]},{"id":"41ae035d.4dcbcc","type":"mqtt in","z":"9c834b39.564c48","name":"","topic":"alarm/sensor/#","qos":"0","broker":"e2eaf260.27fa1","x":132.9999771118164,"y":1233.9999923706055,"wires":[["a82a4c80.ef515"]]},{"id":"a82a4c80.ef515","type":"function","z":"9c834b39.564c48","name":"Save state","func":"flow.set(msg.topic, msg.payload);\n\nmsg.color = (msg.payload == \"T\") ? \"red\" : \"lime\";\n\nreturn msg;","outputs":1,"noerr":0,"x":322.9999771118164,"y":1233.9999923706055,"wires":[["a4d47e9a.fbb6d"]]},{"id":"a4d47e9a.fbb6d","type":"switch","z":"9c834b39.564c48","name":"","property":"topic","propertyType":"msg","rules":[{"t":"eq","v":"alarm/sensor/pir1","vt":"str"},{"t":"eq","v":"alarm/sensor/pir2","vt":"str"},{"t":"eq","v":"alarm/sensor/pir3","vt":"str"},{"t":"eq","v":"alarm/sensor/pir4","vt":"str"},{"t":"eq","v":"alarm/sensor/pirHW","vt":"str"},{"t":"eq","v":"alarm/sensor/pirLR","vt":"str"},{"t":"eq","v":"alarm/sensor/pirDR","vt":"str"},{"t":"eq","v":"alarm/sensor/door","vt":"str"}],"checkall":"true","outputs":8,"x":502.9999771118164,"y":1233.9999923706055,"wires":[["a4b75ed8.360e8"],["9aa3f3b2.603b6"],["53c3164a.a7aff8"],["b2888781.ef7828"],["c5b613f7.6efae"],["b7efad31.42e9d"],["a6512f9b.37c77"],["89c3f984.190278"]]},{"id":"7ef050e4.9dd9","type":"function","z":"9c834b39.564c48","name":"Heartbeat message","func":"if( msg.payload == \"NO ALARM\")\n{\n    context.set(\"IsDown\", true);    // flag the alarm is down\n\n    var dt = new Date();    // get the current date and time\n\n    msg.topic = \"Alarm missing Heartbeat.\";\n    msg.payload = dt.toDateString() + \" \" + dt.toTimeString();\n\n    return msg;\n}\n\nvar isDown = context.get(\"IsDown\") || false;\n\nif( isDown )\n{\n    context.set(\"IsDown\", false);    // flag the alarm is back\n\n    var dt = new Date();    // get the current date and time\n\n    msg.topic = \"Alarm Heartbeat back.\";\n    msg.payload = dt.toDateString() + \" \" + dt.toTimeString();\n    \n    return msg;\n}\n\nreturn null;","outputs":1,"noerr":0,"x":530,"y":720,"wires":[[]]},{"id":"8a9d74a1.e7d228","type":"mqtt out","z":"8cb3e04d.83f54","name":"","topic":"cmnd/LightHW/POWER","qos":"","retain":"","broker":"e2eaf260.27fa1","x":830,"y":340,"wires":[]},{"id":"738b7e7.a49aa8","type":"inject","z":"8cb3e04d.83f54","name":"","repeat":"","crontab":"","once":false,"topic":"","payload":"ON","payloadType":"str","x":110,"y":240,"wires":[["bbca3c6e.ed129","8a9d74a1.e7d228","3ec3931c.35645c"]]},{"id":"b5591712.a86b98","type":"mqtt in","z":"9c834b39.564c48","name":"login","topic":"sys/login/name","qos":"0","broker":"e2eaf260.27fa1","x":90,"y":760,"wires":[["891955b5.044768"]]},{"id":"e8ce5b9e.8eb988","type":"mqtt in","z":"9c834b39.564c48","name":"","topic":"alarm/status","qos":"0","broker":"e2eaf260.27fa1","x":110,"y":960,"wires":[["bb9197cc.5259c8"]]},{"id":"bb9197cc.5259c8","type":"ui_text","z":"9c834b39.564c48","group":"b6867966.7e4de8","order":2,"width":"2","height":"1","name":"Status","label":"","format":"{{msg.payload}}","layout":"row-center","x":730,"y":960,"wires":[]},{"id":"891955b5.044768","type":"function","z":"9c834b39.564c48","name":"Login message","func":"var dt = new Date();    // get the current date and time\n\nmsg.payload += \" login at: \" + dt.toDateString() + \" \" + dt.toTimeString();\n\nmsg.topic = \"Alarm Login.\";\n\nreturn msg;","outputs":1,"noerr":0,"x":520,"y":760,"wires":[["55ef4705.9df718"]]},{"id":"d8ddf3d4.d173a","type":"inject","z":"8cb3e04d.83f54","name":"","repeat":"","crontab":"","once":false,"topic":"","payload":"OFF","payloadType":"str","x":110,"y":320,"wires":[["bbca3c6e.ed129","8a9d74a1.e7d228","3ec3931c.35645c"]]},{"id":"eab70576.fc6078","type":"ui_text","z":"9c834b39.564c48","group":"b6867966.7e4de8","order":4,"width":"4","height":"1","name":"Version","label":"Version","format":"{{msg.payload.Version}}","layout":"row-center","x":727.0000228881836,"y":1026.0000076293945,"wires":[]},{"id":"a6512f9b.37c77","type":"ui_text","z":"9c834b39.564c48","group":"b6867966.7e4de8","order":10,"width":"1","height":"1","name":"","label":"DR","format":"<font color={{msg.color}} ><i class=\"fa fa-circle\" style=\"font-size:24px;\"></i></font>","layout":"col-center","x":722.9999771118164,"y":1333.9999923706055,"wires":[]},{"id":"89c3f984.190278","type":"ui_text","z":"9c834b39.564c48","group":"b6867966.7e4de8","order":7,"width":"1","height":"1","name":"","label":"DOOR","format":"<font color={{msg.color}} ><i class=\"fa fa-circle\" style=\"font-size:24px;\"></i></font>","layout":"col-center","x":722.9999771118164,"y":1373.9999923706055,"wires":[]},{"id":"b7efad31.42e9d","type":"ui_text","z":"9c834b39.564c48","group":"b6867966.7e4de8","order":9,"width":"1","height":"1","name":"","label":"LR","format":"<font color={{msg.color}} ><i class=\"fa fa-circle\" style=\"font-size:24px;\"></i></font>","layout":"col-center","x":722.9999771118164,"y":1293.9999923706055,"wires":[]},{"id":"c5b613f7.6efae","type":"ui_text","z":"9c834b39.564c48","group":"b6867966.7e4de8","order":8,"width":"1","height":"1","name":"","label":"HW","format":"<font color={{msg.color}} ><i class=\"fa fa-circle\" style=\"font-size:24px;\"></i></font>","layout":"col-center","x":722.9999771118164,"y":1253.9999923706055,"wires":[]},{"id":"b2888781.ef7828","type":"ui_text","z":"9c834b39.564c48","group":"b6867966.7e4de8","order":14,"width":"1","height":"1","name":"","label":"pir4","format":"<font color={{msg.color}} ><i class=\"fa fa-circle\" style=\"font-size:24px;\"></i></font>","layout":"col-center","x":722.9999771118164,"y":1213.9999923706055,"wires":[]},{"id":"53c3164a.a7aff8","type":"ui_text","z":"9c834b39.564c48","group":"b6867966.7e4de8","order":13,"width":"1","height":"1","name":"","label":"pir3","format":"<font color={{msg.color}} ><i class=\"fa fa-circle\" style=\"font-size:24px;\"></i></font>","layout":"col-center","x":722.9999771118164,"y":1173.9999923706055,"wires":[]},{"id":"9aa3f3b2.603b6","type":"ui_text","z":"9c834b39.564c48","group":"b6867966.7e4de8","order":12,"width":"1","height":"1","name":"","label":"pir2","format":"<font color={{msg.color}} ><i class=\"fa fa-circle\" style=\"font-size:24px;\"></i></font>","layout":"col-center","x":722.9999771118164,"y":1133.9999923706055,"wires":[]},{"id":"a4b75ed8.360e8","type":"ui_text","z":"9c834b39.564c48","group":"b6867966.7e4de8","order":11,"width":"1","height":"1","name":"","label":"pir1","format":"<font color={{msg.color}} ><i class=\"fa fa-circle\" style=\"font-size:24px;\"></i></font>","layout":"col-center","x":722.9999771118164,"y":1093.9999923706055,"wires":[]},{"id":"46c2f02b.4dc23","type":"function","z":"9c834b39.564c48","name":"Save state","func":"msg.color = (msg.payload == \"Valid\") ? \"red\" : \"lime\";\n\nreturn msg;","outputs":1,"noerr":0,"x":322.9999771118164,"y":1413.9999923706055,"wires":[[]]},{"id":"40ff93e2.c4fdcc","type":"inject","z":"9c834b39.564c48","name":"","repeat":"","crontab":"","once":false,"topic":"","payload":"ARM","payloadType":"str","x":190,"y":800,"wires":[["46264e44.91c3f"]]},{"id":"896a5f1f.25155","type":"inject","z":"9c834b39.564c48","name":"","repeat":"","crontab":"","once":false,"topic":"","payload":"DIS","payloadType":"str","x":190,"y":840,"wires":[["46264e44.91c3f"]]},{"id":"62bf7467.07053c","type":"function","z":"8cb3e04d.83f54","name":"Check Lux","func":"// if its bright then ignore\nif( global.get(\"lux\") > 40 )\n    return null\n\nreturn msg;","outputs":1,"noerr":0,"x":400,"y":540,"wires":[["a7ecaa44.bb9b08"]]},{"id":"50cae3b1.e69f9c","type":"inject","z":"8cb3e04d.83f54","name":"","repeat":"","crontab":"*/1 12-22 * * *","once":true,"onceDelay":"","topic":"","payload":"","payloadType":"date","x":130,"y":160,"wires":[["cd86fc00.196308"]]},{"id":"cd86fc00.196308","type":"function","z":"8cb3e04d.83f54","name":"Check Lux","func":"// if its bright then ignore\nif( global.get(\"lux\") > 40 )\n    return null\n\nreturn msg;","outputs":1,"noerr":0,"x":330,"y":160,"wires":[["1d637f01.40f031"]]},{"id":"1d637f01.40f031","type":"trigger","z":"8cb3e04d.83f54","name":"","op1":"ON","op2":"OFF","op1type":"str","op2type":"str","duration":"5","extend":true,"units":"min","reset":"","bytopic":"all","outputs":1,"x":530,"y":160,"wires":[["bbca3c6e.ed129","3ec3931c.35645c"]]},{"id":"8e65920.eb0a97","type":"json","z":"9c834b39.564c48","name":"","pretty":false,"x":206.01736450195312,"y":570.0104484558105,"wires":[["1b3de2b.a4c341d","93a8ad6e.a12f4"]]},{"id":"93a8ad6e.a12f4","type":"function","z":"9c834b39.564c48","name":"Extract Lux","func":"\n// set the current global lux value\nglobal.set('lux', msg.payload.lux)\n\n\n// perform an exponetial moving average on the data values\nconst EMA_ALPHA = 0.3;\n\nvar luxAverage = context.get(\"luxAverage\") || 0.0;\nif( luxAverage > 0.0)\n{\n    luxAverage = EMA_ALPHA * msg.payload.lux + (1.0 - EMA_ALPHA) * luxAverage;\n}\nelse\n    luxAverage = msg.payload.lux;   // no values yet so just seed with the current value\n    \nif( luxAverage > 0.0)\n{\n    context.set(\"luxAverage\", luxAverage);\n\n    // only plot points every 20 seconds\n    var now = Date.now();\n    var luxPlotTime = context.get(\"luxPlotTime\") || now - 999999;\n\n    if(now - luxPlotTime > 20000 )\n    {\n        node.status({text:luxAverage});\n    \n        context.set(\"luxPlotTime\", now);\n    \n        msg.Topic = \"Lux\";\n        msg.payload = luxAverage;\n\n        return msg;\n    }\n}\nreturn null;\n","outputs":1,"noerr":0,"initialize":"","finalize":"","x":410,"y":540,"wires":[["85387ade.29ed38"]]},{"id":"c6c1047.d966cf8","type":"mqtt in","z":"77549aa8.a94944","name":"","topic":"/WiFi/AP/#","qos":"0","broker":"e2eaf260.27fa1","x":106.0173568725586,"y":214.0104217529297,"wires":[["9d826d19.9e5b6"]]},{"id":"bf871c5d.12cc8","type":"switch","z":"77549aa8.a94944","name":"","property":"topic","propertyType":"msg","rules":[{"t":"eq","v":"Uptime","vt":"str"},{"t":"eq","v":"NoStations","vt":"str"},{"t":"eq","v":"Bin","vt":"str"},{"t":"eq","v":"Bout","vt":"str"},{"t":"eq","v":"Ppsin","vt":"str"},{"t":"eq","v":"Ppsout","vt":"str"},{"t":"eq","v":"Bpsin","vt":"str"},{"t":"eq","v":"Bpsout","vt":"str"}],"checkall":"true","repair":false,"outputs":8,"x":496.0173568725586,"y":214.0104217529297,"wires":[["733defb4.4f6cb"],["5b7a5ef3.a302d"],["dbd892f5.f09cd"],["1929169a.3f46f9"],["b817ee41.87c87"],["8c70a3ac.cfaad"],["71047d68.7a2c04"],["124ddcc.b2b5323"]]},{"id":"5b7a5ef3.a302d","type":"ui_text","z":"77549aa8.a94944","group":"a5ed876a.3e1978","order":2,"width":"2","height":"1","name":"","label":"NoStations","format":"{{msg.payload}}","layout":"col-center","x":737.0173301696777,"y":113.01043033599854,"wires":[]},{"id":"124ddcc.b2b5323","type":"ui_text","z":"77549aa8.a94944","group":"a5ed876a.3e1978","order":8,"width":"2","height":"1","name":"","label":"Bpsout","format":"{{msg.payload}}","layout":"col-center","x":718.0173454284668,"y":363.010440826416,"wires":[]},{"id":"8c70a3ac.cfaad","type":"ui_text","z":"77549aa8.a94944","group":"a5ed876a.3e1978","order":6,"width":"2","height":"1","name":"","label":"Ppsout","format":"{{msg.payload}}","layout":"col-center","x":716.0173568725586,"y":274.0104217529297,"wires":[]},{"id":"b817ee41.87c87","type":"ui_text","z":"77549aa8.a94944","group":"a5ed876a.3e1978","order":5,"width":"2","height":"1","name":"","label":"Ppsin","format":"{{msg.payload}}","layout":"col-center","x":716.0173568725586,"y":234.0104217529297,"wires":[]},{"id":"1929169a.3f46f9","type":"ui_text","z":"77549aa8.a94944","group":"a5ed876a.3e1978","order":4,"width":"2","height":"1","name":"","label":"Bout","format":"{{msg.payload}}","layout":"col-center","x":716.0173568725586,"y":194.0104217529297,"wires":[]},{"id":"dbd892f5.f09cd","type":"ui_text","z":"77549aa8.a94944","group":"a5ed876a.3e1978","order":3,"width":"2","height":"1","name":"","label":"Bin","format":"{{msg.payload}}","layout":"col-center","x":716.0173568725586,"y":154.0104217529297,"wires":[]},{"id":"71047d68.7a2c04","type":"ui_text","z":"77549aa8.a94944","group":"a5ed876a.3e1978","order":7,"width":"2","height":"1","name":"","label":"Bpsin","format":"{{msg.payload}}","layout":"col-center","x":719.0173454284668,"y":319.010404586792,"wires":[]},{"id":"733defb4.4f6cb","type":"ui_text","z":"77549aa8.a94944","group":"a5ed876a.3e1978","order":1,"width":"2","height":"1","name":"","label":"UpTime","format":"{{msg.payload}}","layout":"col-center","x":726.0173568725586,"y":74.01042175292969,"wires":[]},{"id":"9d826d19.9e5b6","type":"function","z":"77549aa8.a94944","name":"Strip topic","func":"\n// strip off the leading /WiFi/AP/sys/\nmsg.topic = msg.topic.substr(13);\n\nreturn msg;","outputs":1,"noerr":0,"x":306.0173568725586,"y":214.0104217529297,"wires":[["bf871c5d.12cc8"]]},{"id":"aebd0bc.7bc62f8","type":"mqtt in","z":"77549aa8.a94944","name":"","topic":"/WiFi/EspR/#","qos":"0","broker":"e2eaf260.27fa1","x":115.0173568725586,"y":595.0104370117188,"wires":[["ebe494e8.cfb9b8"]]},{"id":"964530d0.b46ba","type":"switch","z":"77549aa8.a94944","name":"","property":"topic","propertyType":"msg","rules":[{"t":"eq","v":"Uptime","vt":"str"},{"t":"eq","v":"NoStations","vt":"str"},{"t":"eq","v":"Bin","vt":"str"},{"t":"eq","v":"Bout","vt":"str"},{"t":"eq","v":"Ppsin","vt":"str"},{"t":"eq","v":"Ppsout","vt":"str"},{"t":"eq","v":"Bpsin","vt":"str"},{"t":"eq","v":"Bpsout","vt":"str"}],"checkall":"true","repair":false,"outputs":8,"x":495.0173568725586,"y":595.0104370117188,"wires":[["4d9c089b.d1cf88"],["a15cf2e.6cac91"],["d236a1ff.0bda5"],["4a947a8f.e11114"],["67cdc5b0.d29dac"],["6acc6b6c.1f5254"],["d2251c95.3cf1e"],["d51cc492.c3cdb8"]]},{"id":"a15cf2e.6cac91","type":"ui_text","z":"77549aa8.a94944","group":"ed92ea3f.c10ff8","order":2,"width":"2","height":"1","name":"","label":"NoStations","format":"{{msg.payload}}","layout":"col-center","x":736.0173301696777,"y":494.0104455947876,"wires":[]},{"id":"d51cc492.c3cdb8","type":"ui_text","z":"77549aa8.a94944","group":"ed92ea3f.c10ff8","order":8,"width":"2","height":"1","name":"","label":"Bpsout","format":"{{msg.payload}}","layout":"col-center","x":717.0173454284668,"y":744.0104560852051,"wires":[]},{"id":"6acc6b6c.1f5254","type":"ui_text","z":"77549aa8.a94944","group":"ed92ea3f.c10ff8","order":6,"width":"2","height":"1","name":"","label":"Ppsout","format":"{{msg.payload}}","layout":"col-center","x":715.0173568725586,"y":655.0104370117188,"wires":[]},{"id":"67cdc5b0.d29dac","type":"ui_text","z":"77549aa8.a94944","group":"ed92ea3f.c10ff8","order":5,"width":"2","height":"1","name":"","label":"Ppsin","format":"{{msg.payload}}","layout":"col-center","x":715.0173568725586,"y":615.0104370117188,"wires":[]},{"id":"4a947a8f.e11114","type":"ui_text","z":"77549aa8.a94944","group":"ed92ea3f.c10ff8","order":4,"width":"2","height":"1","name":"","label":"Bout","format":"{{msg.payload}}","layout":"col-center","x":715.0173568725586,"y":575.0104370117188,"wires":[]},{"id":"d236a1ff.0bda5","type":"ui_text","z":"77549aa8.a94944","group":"ed92ea3f.c10ff8","order":3,"width":"2","height":"1","name":"","label":"Bin","format":"{{msg.payload}}","layout":"col-center","x":715.0173568725586,"y":535.0104370117188,"wires":[]},{"id":"d2251c95.3cf1e","type":"ui_text","z":"77549aa8.a94944","group":"ed92ea3f.c10ff8","order":7,"width":"2","height":"1","name":"","label":"Bpsin","format":"{{msg.payload}}","layout":"col-center","x":718.0173454284668,"y":700.010419845581,"wires":[]},{"id":"4d9c089b.d1cf88","type":"ui_text","z":"77549aa8.a94944","group":"ed92ea3f.c10ff8","order":1,"width":"2","height":"1","name":"","label":"UpTime","format":"{{msg.payload}}","layout":"col-center","x":725.0173568725586,"y":455.01043701171875,"wires":[]},{"id":"ebe494e8.cfb9b8","type":"function","z":"77549aa8.a94944","name":"Strip topic","func":"\n// strip off the leading /WiFi/EspR/sys/\nmsg.topic = msg.topic.substr(15);\n\nreturn msg;","outputs":1,"noerr":0,"x":305.0173568725586,"y":595.0104370117188,"wires":[["964530d0.b46ba"]]},{"id":"40af7a64.aabba4","type":"mqtt in","z":"19e925d9.c9f0ba","name":"","topic":"#","qos":"2","broker":"e2eaf260.27fa1","x":90,"y":100,"wires":[["99453e7d.36b1f","e7fecf9e.ecfe6"]]},{"id":"99453e7d.36b1f","type":"function","z":"19e925d9.c9f0ba","name":"Store and shift msg","func":"if(msg.topic.indexOf( \"/WiFi/\") === 0)    \n    return null;\n    \nif(msg.topic.indexOf( \"Weather/\") === 0)    \n    return null;\n\nif(msg.topic.indexOf( \"ESPClock/\") === 0)    \n    return null;\n\n// filter out some high frequency messages\nif( msg.topic == \"alarm/heartbeat\")\n    return null;\n\n// filter out telemetry messages    \nif(msg.topic.indexOf( \"tele/\") === 0)    \n    return null;\n\n// filter out PIR messages\nif(msg.topic.indexOf(\"alarm/sensor/pir\") === 0)   \n    return null;\n\n// filter out Soil Moisture Monitor messages\nif(msg.topic.indexOf(\"SoilMoisture\") === 0)   \n    return null;\n\n// filter out LDR messages\nif(msg.topic.indexOf(\"ESPClock/ldr\") === 0)   \n    return null;\n\ndate = new Date();\nmsg.time = date.toTimeString().split(' ')[0];\n\n// initialise the counter to 0 if it doesn't exist already\nvar text = context.get('text') || [];\n\ntext.push(msg);\n\nif (text.length > 20){\n    text.shift();\n    text.length = 20;\n} \n\n// store the value back\ncontext.set('text',text);\n// make it part of the outgoing msg object\nmsg = {};\nmsg.payload = text;\nreturn msg;\n","outputs":1,"noerr":0,"x":370,"y":100,"wires":[["d3767215.653f4"]]},{"id":"d3767215.653f4","type":"ui_template","z":"19e925d9.c9f0ba","group":"824cf83e.293e98","name":"MQTT Log","order":1,"width":"16","height":"8","format":"<ul ng-style=\"{'white-space': 'nowrap'}\">\n <li ng-repeat=\"x in msg.payload\">\n <font size=\"2\" color=\"blue\">{{x.time}}</font>\n <font size=\"2\" color=\"red\">{{x.topic}}</font>\n <font size=\"2\" color=\"white\"> {{x.payload}}</font>\n </li>\n</ul>","storeOutMessages":true,"fwdInMessages":true,"templateScope":"local","x":750,"y":100,"wires":[[]]},{"id":"e7fecf9e.ecfe6","type":"debug","z":"19e925d9.c9f0ba","name":"","active":false,"console":"false","complete":"false","x":366.0000228881836,"y":167.00000953674316,"wires":[]},{"id":"dad0cb60.5f4868","type":"ui_text","z":"8cb3e04d.83f54","group":"b6867966.7e4de8","order":5,"width":"2","height":"1","name":"","label":"Light LR","format":"<font color={{msg.color}} ><i class=\"fa fa-circle\" style=\"font-size:24px;\"></i></font>","layout":"row-center","x":680,"y":80,"wires":[]},{"id":"3c4982d8.18751e","type":"ui_text","z":"8cb3e04d.83f54","group":"b6867966.7e4de8","order":6,"width":"2","height":"1","name":"","label":"Light HW","format":"<font color={{msg.color}} ><i class=\"fa fa-circle\" style=\"font-size:24px;\"></i></font>","layout":"row-center","x":680,"y":40,"wires":[]},{"id":"c811e45d.49ab68","type":"mqtt in","z":"8cb3e04d.83f54","name":"","topic":"stat/LightHW/POWER","qos":"0","broker":"e2eaf260.27fa1","x":140,"y":40,"wires":[["a11165cd.693ba8"]]},{"id":"8f8584f8.2bab38","type":"mqtt in","z":"8cb3e04d.83f54","name":"","topic":"stat/LightLR/POWER1","qos":"0","broker":"e2eaf260.27fa1","x":140,"y":80,"wires":[["39087230.00006e"]]},{"id":"a11165cd.693ba8","type":"function","z":"8cb3e04d.83f54","name":"Light State","func":"msg.color = (msg.payload == \"ON\") ? \"blue\" : \"gray\";\n\nreturn msg;","outputs":1,"noerr":0,"x":430,"y":40,"wires":[["3c4982d8.18751e"]]},{"id":"39087230.00006e","type":"function","z":"8cb3e04d.83f54","name":"Light State","func":"msg.color = (msg.payload == \"ON\") ? \"blue\" : \"gray\";\n\nreturn msg;","outputs":1,"noerr":0,"x":430,"y":80,"wires":[["dad0cb60.5f4868"]]},{"id":"3bb36e5a.64de62","type":"ui_toast","z":"9c834b39.564c48","position":"bottom right","displayTime":"5","highlight":"Red","outputs":0,"ok":"OK","cancel":"","topic":"","name":"","x":625.9999542236328,"y":1487.999984741211,"wires":[]},{"id":"1b8e3cc6.05afc3","type":"mqtt in","z":"9c834b39.564c48","name":"","topic":"CID","qos":"0","broker":"e2eaf260.27fa1","x":95.99995422363281,"y":1487.999984741211,"wires":[["3bb36e5a.64de62"]]},{"id":"42763b57.5ab144","type":"tcp in","z":"d087fa29.08fdc8","name":"","server":"client","host":"192.168.1.231","port":"3333","datamode":"stream","datatype":"utf8","newline":"\\n","topic":"","base64":false,"x":160,"y":120,"wires":[["c3be637e.fd658","8109a6f3.ee6178"]]},{"id":"ce83c355.e1f9e","type":"inject","z":"d087fa29.08fdc8","name":"Keep Awake","repeat":"60","crontab":"","once":false,"onceDelay":0.1,"topic":"","payload":"REQ: YO\\n","payloadType":"str","x":300,"y":420,"wires":[["923f3c7c.8b6c"]]},{"id":"bb712277.8e702","type":"comment","z":"d087fa29.08fdc8","name":"Interface to NCID","info":"","x":140,"y":40,"wires":[]},{"id":"50c71a77.920124","type":"ui_template","z":"d087fa29.08fdc8","group":"9a6c950b.59f2e8","name":"CID Log","order":2,"width":"6","height":"8","format":"<div style=\"margin: 8px\">\n    <div ng-repeat=\"x in msg.payload\">\n        <span style=\"display: inline-block; width: 75px\">\n            <font color=\"{{x.NAME === 'NO NAME' ? 'red' : 'yellow'}}\" size=\"2\">{{x.NAME}}</font>\n        </span>\n        <span ng-if=\"x.NAME === 'NO NAME'\">\n            <a ng-href=\"https://who-called.co.uk/Number/{{x.NMBR}}\" target=\"_whoCalledMe\">\n                <font size=\"2\" color=\"white\">{{x.NMBR}} {{x.DATE}} {{x.TIME}}</font>\n            </a>\n        </span>\n        <span ng-if=\"x.NAME !== 'NO NAME'\">\n            <font size=\"2\" color=\"lime\">{{x.NMBR}} {{x.DATE}} {{x.TIME}}</font>\n        </span>\n    </div>\n</div>","storeOutMessages":true,"fwdInMessages":true,"templateScope":"local","x":840,"y":120,"wires":[[]]},{"id":"c0588c19.25665","type":"mqtt out","z":"9c834b39.564c48","name":"","topic":"","qos":"","retain":"","broker":"e2eaf260.27fa1","x":586.9999694824219,"y":1783.6771087646484,"wires":[]},{"id":"cbbf3ef8.09eb7","type":"inject","z":"9c834b39.564c48","name":"Time Sync","repeat":"3600","crontab":"","once":true,"topic":"sys/sync/timestamp","payload":"","payloadType":"date","x":246.99996948242188,"y":1783.6771087646484,"wires":[["c0588c19.25665"]]},{"id":"a57d915d.8ecf5","type":"inject","z":"9c834b39.564c48","name":"cmd/alarm/rfid/add","repeat":"","crontab":"","once":false,"topic":"cmd/alarm/rfid/add","payload":"{\"uid\":[90,113,101,217]}","payloadType":"json","x":269.99996185302734,"y":1585.6770858764648,"wires":[["c1d9e15e.75199"]]},{"id":"c1d9e15e.75199","type":"mqtt out","z":"9c834b39.564c48","name":"","topic":"","qos":"","retain":"","broker":"e2eaf260.27fa1","x":609.9999618530273,"y":1645.6770858764648,"wires":[]},{"id":"8ca939d0.8e4e28","type":"inject","z":"9c834b39.564c48","name":"","repeat":"","crontab":"","once":false,"topic":"cmd/alarm/code/del","payload":"3105","payloadType":"str","x":289.99996185302734,"y":1705.6770858764648,"wires":[["c1d9e15e.75199"]]},{"id":"73205e7d.2e207","type":"inject","z":"9c834b39.564c48","name":"cmd/alarm/rfid/master","repeat":"","crontab":"","once":false,"topic":"cmd/alarm/rfid/master","payload":"{\"uid\":[50,60,213,17]}","payloadType":"json","x":279.99996185302734,"y":1645.6770858764648,"wires":[["c1d9e15e.75199"]]},{"id":"c3be637e.fd658","type":"function","z":"d087fa29.08fdc8","name":"Parse Input","func":"// convert a call line to an object\nfunction toObject(str)\n{\n    var items = str.split(\"*\");\n    \n    var data = {};\n    data.Type = items[0].trim();\n    for(var i = 1; i < items.length; i += 2)\n        data[items[i]] = items[i+1];\n        \n        \n    // reformat the date and time fields\n    if(data.hasOwnProperty(\"DATE\"))\n        data.DATE = data.DATE.slice(2,4) + \"-\" + data.DATE.slice(0,2) + \"-\" + data.DATE.slice(4);\n    if(data.hasOwnProperty(\"TIME\"))\n        data.TIME = data.TIME.slice(0,2) + \":\" + data.TIME.slice(2);\n\n    return data;\n}\n\nfunction isOneOf(itms)\n{\n    for(var i = 0; i < itms.length; ++i)\n        if( msg.payload.startsWith(itms[i]) === true)\n            return true;\n    return false;\n}\n\nflow.set(\"SESSION\", msg._session);  // remember the session\n\n\n// detect and parse out any call log messages\nif( isOneOf([\"CID:\", \"CIDLOG:\", \"CIDINFO:\", \"CALLINFO:\", \"MSGLOG:\", \"MSG:\", \"END:\",\"HUP:\",\"LOG:\",\"INFO:\", \"OPT:\"]))\n    return [toObject(msg.payload), null, null];\n\n// detect response messages\nif( isOneOf([\"200\",\"210\",\"250\",\"251\",\"252\",\"253\",\"300\",\"400\",\"401\",\"402\",\"403\",\"410\",\"411\"]))\n    return [null,msg,null];\n\n\n// anything else\nreturn [null,null,msg];","outputs":3,"noerr":0,"x":170,"y":220,"wires":[["67d65472.4fce6c"],["5b4e40b2.28b7f"],["bad4830f.7dce1"]],"outputLabels":["call type","response","other"]},{"id":"bad4830f.7dce1","type":"debug","z":"d087fa29.08fdc8","name":"","active":false,"tosidebar":true,"console":false,"tostatus":false,"complete":"true","x":430,"y":280,"wires":[]},{"id":"5b4e40b2.28b7f","type":"function","z":"d087fa29.08fdc8","name":"Responses","func":"// Server API message\nif(msg.payload.startsWith(\"210 \") === true)\n{\n    return [{payload:\"HELLO: IDENT: client node-red\\n\"}, null];\n}\n\n//End of connection startup\nif(msg.payload.startsWith(\"300 \") === true)\n{\n    return [{payload:\"REQ: ACK\\n\"},null];\n}\n\n// end of call log\nif(msg.payload.startsWith(\"250 \") === true)\n{\n    return [null,null];\n}\n\n// server ident\nif(msg.payload.startsWith(\"200 \") === true)\n{\n    return [null,null];\n}\n\n\nreturn [null,msg];\n","outputs":2,"noerr":0,"x":450,"y":220,"wires":[["e9329d64.aac1c"],["f93aa23.c5ae26"]],"outputLabels":["output","other"]},{"id":"67d65472.4fce6c","type":"function","z":"d087fa29.08fdc8","name":"Handle Call records","func":"function addToCallLog(data)\n{\n    // initialise the array if it doesn't exist already\n    var cidlog = flow.get('cidlog') || [];\n\n    cidlog.unshift(msg); // insert at the start of the array\n\n    while (cidlog.length > 20) // remember the last n logs\n        cidlog.pop();   // remove from the end\n\n    // store the value back\n    flow.set('cidlog',cidlog);\n    return cidlog;\n}\n\n\nif( msg.Type === \"CIDLOG:\")\n{\n    return [{payload:addToCallLog(msg)}, msg, null];\n}\n\n\n// process the CID record\nif( msg.Type === \"CID:\")\n{\n    flow.set(\"NMBR\", msg.NMBR);\n    flow.set(\"NAME\", msg.NAME);\n\n    return [{payload:addToCallLog(msg)}, msg, null];\n}\n\nreturn [null,null,null];","outputs":3,"noerr":0,"x":470,"y":140,"wires":[["50c71a77.920124"],[],["e9329d64.aac1c"]],"outputLabels":["cidlog","cid","update"]},{"id":"a47543ea.ceddf","type":"ui_toast","z":"d087fa29.08fdc8","position":"top right","displayTime":"10","highlight":"","outputs":0,"ok":"OK","cancel":"","topic":"","name":"","x":920,"y":600,"wires":[]},{"id":"f93aa23.c5ae26","type":"debug","z":"d087fa29.08fdc8","name":"","active":true,"tosidebar":true,"console":false,"tostatus":false,"complete":"true","x":670,"y":280,"wires":[]},{"id":"8109a6f3.ee6178","type":"debug","z":"d087fa29.08fdc8","name":"","active":false,"tosidebar":true,"console":false,"tostatus":false,"complete":"true","x":430.08331298828125,"y":68.59721946716309,"wires":[]},{"id":"e9329d64.aac1c","type":"function","z":"d087fa29.08fdc8","name":"Add session","func":"msg._session = flow.get(\"SESSION\");\n\nreturn msg;","outputs":1,"noerr":0,"x":670,"y":500,"wires":[["a47543ea.ceddf","25e7b95f.f12626","acd61bfc.c839b8"]]},{"id":"25e7b95f.f12626","type":"debug","z":"d087fa29.08fdc8","name":"","active":true,"tosidebar":true,"console":false,"tostatus":false,"complete":"true","x":890,"y":540,"wires":[]},{"id":"41e00e3.01f5ff","type":"function","z":"d087fa29.08fdc8","name":"Reread call log","func":"// clear the call log\nflow.set('cidlog',[]);\n\nmsg.payload = \"REQ: REREAD\\n\";\nreturn msg;","outputs":1,"noerr":0,"x":300,"y":500,"wires":[["e9329d64.aac1c"]]},{"id":"923f3c7c.8b6c","type":"function","z":"d087fa29.08fdc8","name":"Add session","func":"msg._session = flow.get(\"SESSION\");\n\nreturn msg;","outputs":1,"noerr":0,"x":670,"y":420,"wires":[["acd61bfc.c839b8"]]},{"id":"acd61bfc.c839b8","type":"tcp out","z":"d087fa29.08fdc8","host":"","port":"","beserver":"reply","base64":false,"end":false,"name":"","x":920,"y":440,"wires":[]},{"id":"85387ade.29ed38","type":"ui_chart","z":"9c834b39.564c48","name":"Lux Chart","group":"9faad522.25f398","order":1,"width":"9","height":"3","label":"Lux {{msg.payload | number : '2'}}","chartType":"line","legend":"false","xformat":"dd HH:mm","interpolate":"linear","nodata":"","dot":false,"ymin":"","ymax":"","removeOlder":"1","removeOlderPoints":"","removeOlderUnit":"604800","cutout":0,"useOneColor":false,"colors":["#1f77b4","#aec7e8","#ff7f0e","#2ca02c","#98df8a","#d62728","#ff9896","#9467bd","#c5b0d5"],"outputs":1,"x":720,"y":560,"wires":[[]]},{"id":"43722e05.b18c5","type":"mqtt in","z":"9c834b39.564c48","name":"","topic":"SoilMoisture/left/value","qos":"0","broker":"e2eaf260.27fa1","x":120,"y":480,"wires":[["459bac53.9ec324"]]},{"id":"a4cb446.a6dd2b8","type":"function","z":"9c834b39.564c48","name":"Check Alive and Email","func":"if( msg.topic == \"CheckAlive\")\n{\n    timestamp = context.get('CheckAlive') || 0;\n    \n    if( timestamp !== 0)\n        return [{payload:0},null,{payload:\"Soil Monitor Down since: \" + timestamp}];\n        \n    context.set('CheckAlive', msg.payload);\n    return [null,null,null];\n}\n// zero the keep alive timestamp value\ncontext.set('CheckAlive', 0);\n\n// convert to percent\nvar value = parseInt(msg.payload);\nvar divisor = 850-430;\nvar percent = 100 - (value - 430) * 100 / divisor\n\nmsg.payload = percent;\nnode.status({text:percent});\n \n// hysteresis for sending an email\nvar emailSent = context.get('emailSent') || false;\n\nif( emailSent === false && percent < 30 )\n{\n    context.set(\"emailSent\", true);\n    return [msg, {topic:\"Front left Bay tree\", payload:\"Plant needs a drink!\"}, null];\n}\n\nif(emailSent && percent > 50 )\n{\n    context.set(\"emailSent\", false);\n}\n    \nreturn [msg, null, null];","outputs":3,"noerr":0,"x":440,"y":360,"wires":[["2cd2443.c87f6bc"],["de77857f.dbbe88","f28e204d.78689"],["efdf497f.a48818"]],"info":"Checks that the soil moisture monitor is still sending \nvalues, \nthe CheckAlive timestamp is used to tell if we \nhave seen a message recently."},{"id":"de77857f.dbbe88","type":"e-mail","z":"9c834b39.564c48","server":"smtp.gmail.com","port":"465","secure":true,"name":"graham.knight@lastdayofmay.co.uk","dname":"","x":820,"y":360,"wires":[]},{"id":"f28e204d.78689","type":"e-mail","z":"9c834b39.564c48","server":"smtp.gmail.com","port":"465","secure":true,"name":"gill.knight@lastdayofmay.co.uk","dname":"","x":830,"y":400,"wires":[]},{"id":"af28bccc.63683","type":"inject","z":"9c834b39.564c48","name":"","repeat":"900","crontab":"","once":false,"onceDelay":0.1,"topic":"CheckAlive","payload":"","payloadType":"date","x":150,"y":360,"wires":[["a4cb446.a6dd2b8"]]},{"id":"efdf497f.a48818","type":"ui_toast","z":"9c834b39.564c48","position":"top left","displayTime":"10","highlight":"","outputs":0,"ok":"OK","cancel":"","topic":"","name":"","x":830,"y":440,"wires":[]},{"id":"d46a9a57.099d18","type":"inject","z":"9c834b39.564c48","name":"","repeat":"","crontab":"","once":false,"onceDelay":0.1,"topic":"Test Message","payload":"Test Message","payloadType":"str","x":740,"y":660,"wires":[["55ef4705.9df718"]]},{"id":"d9194530.d74668","type":"inject","z":"32eaa2f3.09c81e","name":"Refresh Timer","repeat":"600","crontab":"","once":false,"onceDelay":"","topic":"Refresh Timer","payload":"true","payloadType":"bool","x":140,"y":200,"wires":[["4ac54fff.75c53"]]},{"id":"90e121cc.3dd03","type":"ui_button","z":"32eaa2f3.09c81e","name":"Weather Refresh","group":"b6867966.7e4de8","order":15,"width":"3","height":"1","passthru":false,"label":"Refresh Weather","tooltip":"","color":"","bgcolor":"","icon":"fa-refresh","payload":"true","payloadType":"bool","topic":"","x":110,"y":280,"wires":[["4ac54fff.75c53","a3de6ded.411bd"]]},{"id":"4ac54fff.75c53","type":"openweathermap","z":"32eaa2f3.09c81e","name":"Current Weather","wtype":"current","lon":"-0.164998","lat":"50.842121","city":"","country":"","language":"en","x":370,"y":200,"wires":[["70f28166.6ffe8","9148e9c4.7a0d18"]]},{"id":"16f2ab72.15e425","type":"comment","z":"32eaa2f3.09c81e","name":"Open Weather API","info":"","x":230,"y":120,"wires":[]},{"id":"f36c875.679e778","type":"openweathermap","z":"32eaa2f3.09c81e","name":"5 Day Forecast","wtype":"forecast","lon":"-0.164998","lat":"50.842121","city":"","country":"","language":"en","x":360,"y":260,"wires":[["527056d8.216778"]]},{"id":"ad15fc77.eb22f","type":"mqtt in","z":"9c834b39.564c48","name":"","topic":"HotBinTemp/value2","qos":"0","datatype":"auto","broker":"e2eaf260.27fa1","x":110,"y":80,"wires":[["b2ae9288.47233"]]},{"id":"aba2c392.f8fdf","type":"mqtt out","z":"19e925d9.c9f0ba","name":"","topic":"","qos":"","retain":"true","broker":"e2eaf260.27fa1","x":730,"y":280,"wires":[]},{"id":"fe9c6ac7.195a98","type":"ui_form","z":"19e925d9.c9f0ba","name":"","label":"Alarm 0","group":"7c2f62b7.5eac4c","order":1,"width":"4","height":"4","options":[{"label":"Hour","value":"Hour","type":"number","required":true},{"label":"Minute","value":"Minute","type":"number","required":true},{"label":"Days","value":"Days","type":"text","required":false}],"formValue":{"Hour":"","Minute":"","Days":""},"payload":"","submit":"submit","cancel":"cancel","topic":"ESPClock/Set/Alarm0","x":110,"y":260,"wires":[["aba2c392.f8fdf"]]},{"id":"e1fa20c2.8473c","type":"mqtt in","z":"9c834b39.564c48","name":"","topic":"Weather/Today/Pressure","qos":"0","datatype":"auto","broker":"e2eaf260.27fa1","x":130,"y":120,"wires":[["f407621f.e4092"]]},{"id":"cfa03529.8770e8","type":"mqtt in","z":"9c834b39.564c48","name":"","topic":"Weather/Today/Humidity","qos":"0","datatype":"auto","broker":"e2eaf260.27fa1","x":130,"y":160,"wires":[["3169839d.93effc"]]},{"id":"f407621f.e4092","type":"ui_chart","z":"9c834b39.564c48","name":"Pressure Chart","group":"9faad522.25f398","order":2,"width":"9","height":"3","label":"Pressure {{msg.payload}}","chartType":"line","legend":"false","xformat":"dd HH:mm","interpolate":"linear","nodata":"","dot":false,"ymin":"","ymax":"","removeOlder":"1","removeOlderPoints":"","removeOlderUnit":"604800","cutout":0,"useOneColor":false,"colors":["#008000","#aec7e8","#ff7f0e","#2ca02c","#98df8a","#d62728","#ff9896","#9467bd","#c5b0d5"],"outputs":1,"x":760,"y":120,"wires":[[]]},{"id":"55d86634.5b3168","type":"ui_chart","z":"9c834b39.564c48","name":"Humidity Chart","group":"9faad522.25f398","order":3,"width":"9","height":"3","label":"Humidity {{msg.payload}}%","chartType":"line","legend":"false","xformat":"dd HH:mm","interpolate":"linear","nodata":"","dot":false,"ymin":"","ymax":"","removeOlder":"1","removeOlderPoints":"","removeOlderUnit":"604800","cutout":0,"useOneColor":false,"useUTC":false,"colors":["#8080ff","#aec7e8","#ff7f0e","#2ca02c","#98df8a","#d62728","#ff9896","#9467bd","#c5b0d5"],"outputs":1,"useDifferentColor":false,"x":760,"y":160,"wires":[[]]},{"id":"b2ae9288.47233","type":"ui_chart","z":"9c834b39.564c48","name":"Temp Chart","group":"9faad522.25f398","order":4,"width":"9","height":"3","label":"Temp {{msg.payload}}&deg;C","chartType":"line","legend":"false","xformat":"auto","interpolate":"linear","nodata":"","dot":false,"ymin":"","ymax":"","removeOlder":"2","removeOlderPoints":"","removeOlderUnit":"86400","cutout":0,"useOneColor":false,"useUTC":false,"colors":["#bb0000","#7c58fd","#ff7f0e","#2ca02c","#98df8a","#d62728","#ff9896","#9467bd","#c5b0d5"],"outputs":1,"x":750,"y":80,"wires":[[]]},{"id":"e69d9cd9.209cd","type":"ui_form","z":"19e925d9.c9f0ba","name":"","label":"Alarm 1","group":"7c2f62b7.5eac4c","order":2,"width":"4","height":"4","options":[{"label":"Hour","value":"Hour","type":"number","required":true},{"label":"Minute","value":"Minute","type":"number","required":true},{"label":"Days","value":"Days","type":"text","required":false}],"formValue":{"Hour":"","Minute":"","Days":""},"payload":"","submit":"submit","cancel":"cancel","topic":"ESPClock/Set/Alarm1","x":110,"y":300,"wires":[["aba2c392.f8fdf"]]},{"id":"3df8b63d.4227ca","type":"ui_button","z":"19e925d9.c9f0ba","name":"","group":"7c2f62b7.5eac4c","order":3,"width":"2","height":"1","passthru":false,"label":"Delete 0","tooltip":"","color":"","bgcolor":"red","icon":"","payload":"","payloadType":"str","topic":"ESPClock/Set/Alarm0","x":120,"y":360,"wires":[["641ffc03.9a9074"]]},{"id":"70c4d806.61c868","type":"ui_button","z":"19e925d9.c9f0ba","name":"","group":"7c2f62b7.5eac4c","order":5,"width":"2","height":"1","passthru":false,"label":"Delete 1","tooltip":"","color":"","bgcolor":"red","icon":"","payload":"","payloadType":"str","topic":"ESPClock/Set/Alarm1","x":120,"y":400,"wires":[["641ffc03.9a9074"]]},{"id":"641ffc03.9a9074","type":"function","z":"19e925d9.c9f0ba","name":"Blank the payload","func":"msg.payload=null;\nreturn msg;","outputs":1,"noerr":0,"x":410,"y":380,"wires":[["e778e7e4.4373a8"]]},{"id":"8c560fd3.d1c14","type":"inject","z":"19e925d9.c9f0ba","name":"","repeat":"","crontab":"","once":false,"onceDelay":0.1,"topic":"ESPClock/Set/Alarm","payload":"","payloadType":"str","x":400,"y":460,"wires":[["e778e7e4.4373a8"]]},{"id":"e778e7e4.4373a8","type":"mqtt out","z":"19e925d9.c9f0ba","name":"","topic":"","qos":"","retain":"true","broker":"e2eaf260.27fa1","x":730,"y":420,"wires":[]},{"id":"70f28166.6ffe8","type":"function","z":"32eaa2f3.09c81e","name":"Split into individual messages","func":"// break out the message into multiple messages\n\nvar condition = {topic:\"Weather/Today/Condition\", payload:msg.payload.weather};\nvar detail = {topic:\"Weather/Today/Detail\", payload:msg.payload.detail};\nvar clouds = {topic:\"Weather/Today/Clouds\", payload:msg.payload.clouds};\nvar icon = {topic:\"Weather/Today/Icon\", payload:msg.payload.icon};\nvar temp = {topic:\"Weather/Today/Temp\", payload:msg.payload.tempc};\nvar mintemp = {topic:\"Weather/Today/MinTemp\", payload:msg.payload.temp_minc};\nvar maxtemp = {topic:\"Weather/Today/MaxTemp\", payload:msg.payload.temp_maxc};\nvar humidity = {topic:\"Weather/Today/Humidity\", payload:msg.payload.humidity};\nvar pressure = {topic:\"Weather/Today/Pressure\", payload:msg.payload.pressure};\nvar windspeed = {topic:\"Weather/Today/WindSpeed\", payload:msg.payload.windspeed};\nvar winddirection = {topic:\"Weather/Today/WindDirection\", payload:msg.payload.winddirection};\nvar sunrise = {topic:\"Weather/Today/Sunrise\", payload:msg.payload.sunrise};\nvar sunset = {topic:\"Weather/Today/Sunset\", payload:msg.payload.sunset};\n\n// return multiple messages to the single output\nreturn [[condition, detail, clouds, icon, temp, mintemp, maxtemp, humidity, pressure, windspeed, winddirection, sunrise, sunset]];","outputs":1,"noerr":0,"x":610,"y":120,"wires":[["53cd16ce.22ad68"]]},{"id":"527056d8.216778","type":"debug","z":"32eaa2f3.09c81e","name":"","active":false,"tosidebar":true,"console":false,"tostatus":false,"complete":"false","x":650,"y":260,"wires":[]},{"id":"9148e9c4.7a0d18","type":"debug","z":"32eaa2f3.09c81e","name":"","active":false,"tosidebar":true,"console":false,"tostatus":false,"complete":"false","x":650,"y":200,"wires":[]},{"id":"53cd16ce.22ad68","type":"mqtt out","z":"32eaa2f3.09c81e","name":"","topic":"","qos":"","retain":"true","broker":"e2eaf260.27fa1","x":850,"y":120,"wires":[]},{"id":"a3de6ded.411bd","type":"darksky","z":"32eaa2f3.09c81e","darksky":"f16fdd32.15974","name":"","lon":"-0.164998","lat":"50.842121","date":"","time":"","mode":"node","lang":"en","units":"uk2","x":160,"y":480,"wires":[["a47d83c2.e124e"]]},{"id":"a47d83c2.e124e","type":"debug","z":"32eaa2f3.09c81e","name":"","active":false,"tosidebar":true,"console":false,"tostatus":false,"complete":"true","targetType":"full","x":350,"y":480,"wires":[]},{"id":"5d395632.ae95e8","type":"ui_text","z":"32eaa2f3.09c81e","group":"b6867966.7e4de8","order":16,"width":"3","height":"1","name":"Dark Sky link","label":"","format":"<a href=\"https://darksky.net/forecast/50.842121,-0.164998/si12/en\" target=\"_blank\"><font color=\"White\">Dark Sky</font></a>","layout":"col-center","x":70,"y":320,"wires":[]},{"id":"c29f5cff.446b2","type":"debug","z":"9c834b39.564c48","name":"","active":false,"tosidebar":true,"console":false,"tostatus":false,"complete":"false","x":530,"y":1960,"wires":[]},{"id":"2766a418.91727c","type":"function","z":"9c834b39.564c48","name":"Zero Injector","func":"// Injects zeros while the machine is stopped\nlet interval = 10 * 1000;       // interval at which to inject\nlet stoppedString = \"Stopped\";  // expected string in payload when machine is stopped\n\nlet timerId = context.get(\"timerId\") || 0;\n// stop injection if currently active\nif (timerId) {\n    clearTimeout(timerId);\n    timerId = null;\n    context.set(\"timerId\", timerId);\n}\nif (msg.payload == stoppedString) {\n    // machine stopped so start injection\n    timerId = setInterval(function() {\n        node.send({payload: 0})\n    }, interval);\n    context.set(\"timerId\", timerId);\n}","outputs":1,"noerr":0,"x":352,"y":1959,"wires":[["c29f5cff.446b2"]]},{"id":"f55a3021.521a4","type":"inject","z":"9c834b39.564c48","name":"","repeat":"","crontab":"","once":false,"onceDelay":0.1,"topic":"","payload":"Running","payloadType":"str","x":144,"y":1952,"wires":[["2766a418.91727c"]]},{"id":"b4c3a8ce.49e808","type":"inject","z":"9c834b39.564c48","name":"","repeat":"","crontab":"","once":false,"onceDelay":0.1,"topic":"","payload":"Stopped","payloadType":"str","x":143,"y":1999,"wires":[["2766a418.91727c"]]},{"id":"2ae5f888.fbebd8","type":"function","z":"6895dc3b.267224","name":"Smooth and sample","func":"// forward the average every 600 seconds\nconst SAMPLE_MS = 600000;\n\n// perform an exponetial moving average on the data values\nconst EMA_ALPHA = 0.3;\n\nvar average = context.get(\"average\") || 0.0;\nif( average > 0.0)\n{\n    average = EMA_ALPHA * msg.payload + (1.0 - EMA_ALPHA) * average;\n}\nelse\n    average = msg.payload;   // no values yet so just seed with the current value\n    \nif( average > 0.0)\n{\n    context.set(\"average\", average);\n\n    // only plot points every 60 seconds\n    var now = Date.now();\n    var plotTime = context.get(\"plotTime\") || now - 999999;\n\n    if(now - plotTime > SAMPLE_MS )\n    {\n        node.status({text:average});\n    \n        context.set(\"plotTime\", now);\n    \n        msg.Topic = \"Average\";\n        msg.payload = average;\n\n        return msg;\n    }\n}\nreturn null;","outputs":1,"noerr":0,"x":350,"y":40,"wires":[[]]},{"id":"459bac53.9ec324","type":"subflow:6895dc3b.267224","z":"9c834b39.564c48","name":"","env":[],"x":200,"y":420,"wires":[["a4cb446.a6dd2b8","cccf309a.b719"]]},{"id":"2cd2443.c87f6bc","type":"debug","z":"9c834b39.564c48","name":"","active":false,"tosidebar":true,"console":false,"tostatus":false,"complete":"true","targetType":"full","x":910,"y":320,"wires":[]},{"id":"cccf309a.b719","type":"function","z":"9c834b39.564c48","name":"To Percent","func":"\nvar value = parseInt(msg.payload);\nvar divisor = 850-430;\nvar percent = 100 - (value - 430) * 100 / divisor\n\n// invert value\n//var value = 850 - parseInt(msg.payload);\n\n// conver to percent\n//var percent = 100 * value / (850-430);\n\nmsg.payload = percent;\n\nnode.status({text:percent});\n\nreturn msg;","outputs":1,"noerr":0,"x":410,"y":460,"wires":[["c0603ece.db35f"]]},{"id":"c0603ece.db35f","type":"ui_chart","z":"9c834b39.564c48","name":"Soil moisture Chart","group":"9faad522.25f398","order":5,"width":"9","height":"3","label":"Soil Moisture {{msg.payload | number : 1}}%","chartType":"line","legend":"false","xformat":"ddd DD","interpolate":"linear","nodata":"","dot":false,"ymin":"","ymax":"","removeOlder":"7","removeOlderPoints":"","removeOlderUnit":"86400","cutout":0,"useOneColor":false,"useUTC":false,"colors":["#b8911b","#aec7e8","#ff7f0e","#2ca02c","#98df8a","#d62728","#ff9896","#9467bd","#c5b0d5"],"outputs":1,"useDifferentColor":false,"x":650,"y":500,"wires":[[]]},{"id":"3463d874.7d8708","type":"http request","z":"9c834b39.564c48","name":"","method":"GET","ret":"obj","paytoqs":false,"url":"https://www.alphavantage.co/query?function=CURRENCY_EXCHANGE_RATE&from_currency=GBP&to_currency=EUR&apikey=V74A2L2P1R2SO6KF","tls":"","proxy":"","authType":"basic","x":290,"y":2100,"wires":[["75be00f5.fdbf6","fefc791f.2ed2f8"]]},{"id":"dce66173.6a187","type":"inject","z":"9c834b39.564c48","name":"","repeat":"360","crontab":"","once":true,"onceDelay":"5","topic":"","payload":"","payloadType":"date","x":110,"y":2100,"wires":[["3463d874.7d8708"]]},{"id":"e4804837.abd828","type":"ui_chart","z":"9c834b39.564c48","name":"GBPEUR Chart","group":"9faad522.25f398","order":8,"width":"9","height":"4","label":"GBPEUR {{msg.payload | number : '3'}}","chartType":"line","legend":"false","xformat":"dd HH:mm","interpolate":"linear","nodata":"","dot":false,"ymin":"","ymax":"","removeOlder":"48","removeOlderPoints":"","removeOlderUnit":"3600","cutout":0,"useOneColor":false,"colors":["#1f77b4","#aec7e8","#ff7f0e","#2ca02c","#98df8a","#d62728","#ff9896","#9467bd","#c5b0d5"],"outputs":1,"x":680,"y":2100,"wires":[[]]},{"id":"75be00f5.fdbf6","type":"function","z":"9c834b39.564c48","name":"Extract Price","func":"\nreturn { payload: msg.payload['Realtime Currency Exchange Rate']['5. Exchange Rate']}\n\n","outputs":1,"noerr":0,"x":470,"y":2100,"wires":[["e4804837.abd828"]]},{"id":"fae98323.4a79","type":"ui_slider","z":"5e8c75af.480b0c","name":"","label":"Brightness","tooltip":"","group":"5a430243.08a5cc","order":16,"width":0,"height":0,"passthru":true,"outs":"all","topic":"NeoPixel/Brightness","min":0,"max":"255","step":"5","x":150,"y":100,"wires":[["d528730f.5bce1"]]},{"id":"d1a0e03d.4b4cc","type":"mqtt out","z":"5e8c75af.480b0c","name":"","topic":"","qos":"","retain":"false","broker":"e2eaf260.27fa1","x":530,"y":220,"wires":[]},{"id":"77d20eb9.bf1e5","type":"ui_colour_picker","z":"5e8c75af.480b0c","name":"","label":"","group":"5a430243.08a5cc","format":"rgb","outformat":"object","showSwatch":false,"showPicker":true,"showValue":false,"showHue":true,"showAlpha":false,"showLightness":true,"square":"true","dynOutput":"false","order":16,"width":"5","height":"5","passthru":true,"topic":"NeoPixel/RGB","x":150,"y":160,"wires":[["d1a0e03d.4b4cc"]]},{"id":"fec61ab1.6a8808","type":"ui_button","z":"5e8c75af.480b0c","name":"","group":"5a430243.08a5cc","order":2,"width":"2","height":"1","passthru":false,"label":"Rainbow","tooltip":"","color":"","bgcolor":"","icon":"","payload":"1","payloadType":"str","topic":"NeoPixel/Rainbow","x":140,"y":220,"wires":[["d1a0e03d.4b4cc"]]},{"id":"5707a3bc.d0de5c","type":"ui_button","z":"5e8c75af.480b0c","name":"","group":"5a430243.08a5cc","order":16,"width":"2","height":"1","passthru":false,"label":"Flames","tooltip":"","color":"","bgcolor":"","icon":"fa-barcode","payload":"1","payloadType":"str","topic":"NeoPixel/Flames","x":140,"y":280,"wires":[["d1a0e03d.4b4cc"]]},{"id":"690cb382.31b03c","type":"ui_button","z":"5e8c75af.480b0c","name":"","group":"5a430243.08a5cc","order":16,"width":"1","height":"1","passthru":false,"label":"On","tooltip":"","color":"","bgcolor":"","icon":"fa-barcode","payload":"ON","payloadType":"str","topic":"NeoPixel/OnOff","x":130,"y":320,"wires":[["d1a0e03d.4b4cc"]]},{"id":"9a5fb7f2.d71518","type":"ui_ui_control","z":"9c834b39.564c48","name":"Logs Page","x":290,"y":2180,"wires":[[]]},{"id":"8e2a2701.db7c48","type":"ui_ui_control","z":"19e925d9.c9f0ba","name":"","x":280,"y":560,"wires":[[]]},{"id":"b20e9811.8b9138","type":"ui_button","z":"19e925d9.c9f0ba","name":"","group":"7c2f62b7.5eac4c","order":7,"width":0,"height":0,"passthru":false,"label":"Home","tooltip":"","color":"","bgcolor":"","icon":"","payload":"Home","payloadType":"str","topic":"","x":80,"y":560,"wires":[["8e2a2701.db7c48"]]},{"id":"3ec3931c.35645c","type":"mqtt out","z":"8cb3e04d.83f54","name":"","topic":"NeoPixelAmelia/OnOff","qos":"1","retain":"","broker":"e2eaf260.27fa1","x":820,"y":260,"wires":[]},{"id":"1381203f.f4375","type":"ui_button","z":"5e8c75af.480b0c","name":"","group":"5a430243.08a5cc","order":16,"width":"1","height":"1","passthru":false,"label":"Off","tooltip":"","color":"","bgcolor":"","icon":"fa-barcode","payload":"OFF","payloadType":"str","topic":"NeoPixel/OnOff","x":130,"y":360,"wires":[["d1a0e03d.4b4cc"]]},{"id":"d528730f.5bce1","type":"mqtt out","z":"5e8c75af.480b0c","name":"Retained messages","topic":"","qos":"","retain":"true","broker":"e2eaf260.27fa1","x":540,"y":100,"wires":[]},{"id":"fefc791f.2ed2f8","type":"debug","z":"9c834b39.564c48","name":"","active":false,"tosidebar":true,"console":false,"tostatus":false,"complete":"false","x":490,"y":2140,"wires":[]},{"id":"e099c84e.9ecac8","type":"ui_slider","z":"99f288e8.63d4c8","name":"","label":"Brightness","tooltip":"","group":"85002a37.c1c1f8","order":1,"width":"6","height":"1","passthru":true,"outs":"all","topic":"NeoPixelAmelia/Brightness","min":"1","max":"255","step":"1","x":130,"y":100,"wires":[["364bfe07.f82b72"]]},{"id":"9cdeddcb.ce64f","type":"mqtt out","z":"99f288e8.63d4c8","name":"","topic":"","qos":"","retain":"false","broker":"e2eaf260.27fa1","x":510,"y":220,"wires":[]},{"id":"863ac3f5.75962","type":"ui_colour_picker","z":"99f288e8.63d4c8","name":"","label":"","group":"85002a37.c1c1f8","format":"rgb","outformat":"object","showSwatch":false,"showPicker":true,"showValue":false,"showHue":true,"showAlpha":false,"showLightness":true,"square":"true","dynOutput":"false","order":2,"width":"5","height":"4","passthru":true,"topic":"NeoPixelAmelia/RGB","x":130,"y":160,"wires":[["9cdeddcb.ce64f"]]},{"id":"dc4cd98d.7548e8","type":"ui_button","z":"99f288e8.63d4c8","name":"","group":"85002a37.c1c1f8","order":5,"width":"2","height":"1","passthru":false,"label":"Rainbow","tooltip":"","color":"","bgcolor":"","icon":"","payload":"1","payloadType":"str","topic":"NeoPixelAmelia/Rainbow","x":120,"y":220,"wires":[["9cdeddcb.ce64f"]]},{"id":"862e93b9.2b1b","type":"ui_button","z":"99f288e8.63d4c8","name":"","group":"85002a37.c1c1f8","order":6,"width":"2","height":"1","passthru":false,"label":"Flames","tooltip":"","color":"","bgcolor":"","icon":"","payload":"1","payloadType":"str","topic":"NeoPixelAmelia/Flames","x":120,"y":280,"wires":[["9cdeddcb.ce64f"]]},{"id":"4e729228.d3777c","type":"ui_button","z":"99f288e8.63d4c8","name":"","group":"85002a37.c1c1f8","order":3,"width":"1","height":"2","passthru":false,"label":"On","tooltip":"","color":"","bgcolor":"","icon":"","payload":"ON","payloadType":"str","topic":"NeoPixelAmelia/OnOff","x":110,"y":460,"wires":[["9cdeddcb.ce64f"]]},{"id":"7bae4d68.68a344","type":"ui_button","z":"99f288e8.63d4c8","name":"","group":"85002a37.c1c1f8","order":4,"width":"1","height":"2","passthru":false,"label":"Off","tooltip":"","color":"","bgcolor":"","icon":"","payload":"OFF","payloadType":"str","topic":"NeoPixelAmelia/OnOff","x":110,"y":500,"wires":[["9cdeddcb.ce64f"]]},{"id":"364bfe07.f82b72","type":"mqtt out","z":"99f288e8.63d4c8","name":"Retained messages","topic":"","qos":"","retain":"true","broker":"e2eaf260.27fa1","x":520,"y":100,"wires":[]},{"id":"6624df09.3864","type":"ui_button","z":"99f288e8.63d4c8","name":"","group":"85002a37.c1c1f8","order":7,"width":"2","height":"1","passthru":false,"label":"Juggle","tooltip":"","color":"","bgcolor":"","icon":"","payload":"1","payloadType":"str","topic":"NeoPixelAmelia/Juggle","x":110,"y":320,"wires":[["9cdeddcb.ce64f"]]},{"id":"23bb5d93.b64a82","type":"ui_button","z":"99f288e8.63d4c8","name":"","group":"85002a37.c1c1f8","order":8,"width":"2","height":"1","passthru":false,"label":"Bpm","tooltip":"","color":"","bgcolor":"","icon":"","payload":"1","payloadType":"str","topic":"NeoPixelAmelia/Bpm","x":110,"y":360,"wires":[["9cdeddcb.ce64f"]]},{"id":"8500e1.e83c5f2","type":"mqtt in","z":"9c834b39.564c48","name":"","topic":"AirQuality/ppd03","qos":"0","datatype":"auto","broker":"e2eaf260.27fa1","x":120,"y":2300,"wires":[["aa74ae9a.7fac8"]]},{"id":"6fa68b3f.1ef9e4","type":"mqtt in","z":"9c834b39.564c48","name":"","topic":"AirQuality/ppd05","qos":"0","datatype":"auto","broker":"e2eaf260.27fa1","x":120,"y":2360,"wires":[["aa74ae9a.7fac8"]]},{"id":"ddc9d796.8f5a58","type":"mqtt in","z":"9c834b39.564c48","name":"","topic":"AirQuality/ppd10","qos":"0","datatype":"auto","broker":"e2eaf260.27fa1","x":120,"y":2420,"wires":[[]]},{"id":"aa74ae9a.7fac8","type":"ui_chart","z":"9c834b39.564c48","name":"Air Quality Monitor","group":"9faad522.25f398","order":9,"width":"9","height":"4","label":"","chartType":"line","legend":"true","xformat":"HH:mm:ss","interpolate":"linear","nodata":"","dot":false,"ymin":"","ymax":"","removeOlder":1,"removeOlderPoints":"","removeOlderUnit":"86400","cutout":0,"useOneColor":false,"colors":["#1f77b4","#aec7e8","#ff7f0e","#2ca02c","#98df8a","#d62728","#ff9896","#9467bd","#c5b0d5"],"outputs":1,"x":430,"y":2360,"wires":[[]]},{"id":"718197c8.273f78","type":"comment","z":"99f288e8.63d4c8","name":"Amelia Light control","info":"","x":150,"y":60,"wires":[]},{"id":"3e87f073.bdc3c","type":"ui_slider","z":"99f288e8.63d4c8","name":"","label":"Brightness","tooltip":"","group":"b0edfcc5.15995","order":1,"width":"6","height":"1","passthru":true,"outs":"all","topic":"NeoPixelPhoebe/Brightness","min":"1","max":"255","step":"1","x":130,"y":620,"wires":[["ffdc2a43.575ac8"]]},{"id":"f1bafa71.4dbe78","type":"mqtt out","z":"99f288e8.63d4c8","name":"","topic":"","qos":"","retain":"false","broker":"e2eaf260.27fa1","x":510,"y":740,"wires":[]},{"id":"2b6983c9.7e734c","type":"ui_colour_picker","z":"99f288e8.63d4c8","name":"","label":"","group":"b0edfcc5.15995","format":"rgb","outformat":"object","showSwatch":false,"showPicker":true,"showValue":false,"showHue":true,"showAlpha":false,"showLightness":true,"square":"true","dynOutput":"false","order":2,"width":"5","height":"4","passthru":true,"topic":"NeoPixelPhoebe/RGB","x":130,"y":680,"wires":[["f1bafa71.4dbe78"]]},{"id":"b9e980c6.bb3eb","type":"ui_button","z":"99f288e8.63d4c8","name":"","group":"b0edfcc5.15995","order":5,"width":"2","height":"1","passthru":false,"label":"Rainbow","tooltip":"","color":"","bgcolor":"","icon":"","payload":"1","payloadType":"str","topic":"NeoPixelPhoebe/Rainbow","x":120,"y":740,"wires":[["f1bafa71.4dbe78"]]},{"id":"8452d82e.20d1b8","type":"ui_button","z":"99f288e8.63d4c8","name":"","group":"b0edfcc5.15995","order":6,"width":"2","height":"1","passthru":false,"label":"Flames","tooltip":"","color":"","bgcolor":"","icon":"","payload":"1","payloadType":"str","topic":"NeoPixelPhoebe/Flames","x":120,"y":800,"wires":[["f1bafa71.4dbe78"]]},{"id":"70ee5e9b.3942b","type":"ui_button","z":"99f288e8.63d4c8","name":"","group":"b0edfcc5.15995","order":3,"width":"1","height":"2","passthru":false,"label":"On","tooltip":"","color":"","bgcolor":"","icon":"","payload":"ON","payloadType":"str","topic":"NeoPixelPhoebe/OnOff","x":110,"y":980,"wires":[["f1bafa71.4dbe78"]]},{"id":"ae9980b4.9c5f","type":"ui_button","z":"99f288e8.63d4c8","name":"","group":"b0edfcc5.15995","order":4,"width":"1","height":"2","passthru":false,"label":"Off","tooltip":"","color":"","bgcolor":"","icon":"","payload":"OFF","payloadType":"str","topic":"NeoPixelPhoebe/OnOff","x":110,"y":1020,"wires":[["f1bafa71.4dbe78"]]},{"id":"ffdc2a43.575ac8","type":"mqtt out","z":"99f288e8.63d4c8","name":"Retained messages","topic":"","qos":"","retain":"true","broker":"e2eaf260.27fa1","x":520,"y":620,"wires":[]},{"id":"1b7fba95.58f235","type":"ui_button","z":"99f288e8.63d4c8","name":"","group":"b0edfcc5.15995","order":7,"width":"2","height":"1","passthru":false,"label":"Juggle","tooltip":"","color":"","bgcolor":"","icon":"","payload":"1","payloadType":"str","topic":"NeoPixelPhoebe/Juggle","x":110,"y":840,"wires":[["f1bafa71.4dbe78"]]},{"id":"cd941652.a25588","type":"ui_button","z":"99f288e8.63d4c8","name":"","group":"b0edfcc5.15995","order":8,"width":"2","height":"1","passthru":false,"label":"Bpm","tooltip":"","color":"","bgcolor":"","icon":"","payload":"1","payloadType":"str","topic":"NeoPixelPhoebe/Bpm","x":110,"y":880,"wires":[["f1bafa71.4dbe78"]]},{"id":"7636e942.442698","type":"comment","z":"99f288e8.63d4c8","name":"Phoebe Light control","info":"","x":150,"y":580,"wires":[]},{"id":"b29b8821.850688","type":"ui_template","z":"d862700a.a9435","group":"a3d8fcdc.db27f","name":"Nest","order":1,"width":"0","height":"0","format":"<div id=\"thermostat\"></div>\n\n<style>\n\n@import url(http://fonts.googleapis.com/css?family=Open+Sans:300);\n\n#thermostat {\n margin: 0 auto;\n -webkit-tap-highlight-color: rgba(0, 0, 0, 0);\n}\n\n.dial {\n    -webkit-user-select: none;\n    -moz-user-select: none;\n    -ms-user-select: none;\n    user-select: none;\n}\n.dial.away .dial__ico__leaf {\n    visibility: hidden;\n}\n.dial.away .dial__lbl--target {\n    visibility: hidden;\n}\n.dial.away .dial__lbl--target--half {\n    visibility: hidden;\n}\n.dial.away .dial__lbl--away {\n    opacity: 1;\n}\n.dial .dial__shape {\n    -webkit-transition: fill 0.5s;\n    transition: fill 0.5s;\n}\n.dial path.dial__ico__leaf {\n    fill: #13EB13;\n    opacity: 0;\n    -webkit-transition: opacity 0.5s;\n    transition: opacity 0.5s;\n    pointer-events: none;\n}\n.dial.has-leaf .dial__ico__leaf {\n    display: block;\n    opacity: 1;\n    pointer-events: initial;\n}\n.dial__editableIndicator {\n    fill-rule: evenodd;\n    opacity: 0;\n    -webkit-transition: opacity 0.5s;\n    transition: opacity 0.5s;\n}\n.dial--edit path.dial__editableIndicator {\n    fill: white;\n}\n.dial--edit .dial__editableIndicator {\n    opacity: 1;\n}\n.dial--state--off .dial__shape {\n    fill: #3d3c3c;\n}\n.dial--state--heating .dial__shape {\n    fill: #E36304;\n}\n.dial--state--cooling .dial__shape {\n    fill: #007AF1;\n}\n.dial .dial__ticks path {\n    fill: rgba(255, 255, 255, 0.3);\n}\n.dial .dial__ticks path.active {\n    fill: rgba(255, 255, 255, 0.8);\n}\n.dial text {\n    fill: white;\n    text-anchor: middle;\n    font-family: Helvetica, sans-serif;\n    alignment-baseline: central;\n}\n.dial__lbl--target {\n    font-size: 120px;\n    font-weight: bold;\n}\n.dial__lbl--target--half {\n    font-size: 40px;\n    font-weight: bold;\n    opacity: 0;\n    -webkit-transition: opacity 0.1s;\n    transition: opacity 0.1s;\n}\n.dial__lbl--target--half.shown {\n    opacity: 1;\n    -webkit-transition: opacity 0s;\n    transition: opacity 0s;\n}\n.dial__lbl--ambient {\n    font-size: 22px;\n    font-weight: bold;\n}\n.dial__lbl--away {\n    font-size: 72px;\n    font-weight: bold;\n    opacity: 0;\n    pointer-events: none;\n}\n#controls {\n    font-family: Open Sans;\n    background-color: rgba(255, 255, 255, 0.25);\n    padding: 20px;\n    border-radius: 5px;\n    position: absolute;\n    left: 50%;\n    -webkit-transform: translatex(-50%);\n    transform: translatex(-50%);\n    margin-top: 20px;\n}\n#controls label {\n    text-align: left;\n    display: block;\n}\n#controls label span {\n    display: inline-block;\n    width: 200px;\n    text-align: right;\n    font-size: 0.8em;\n    text-transform: uppercase;\n}\n#controls p {\n    margin: 0;\n    margin-bottom: 1em;\n    padding-bottom: 1em;\n    border-bottom: 2px solid #ccc;\n}\n</style>\n<script>\n    var thermostatDial = (function() {\n\t\n\t/*\n\t * Utility functions\n\t */\n\t\n\t// Create an element with proper SVG namespace, optionally setting its attributes and appending it to another element\n\tfunction createSVGElement(tag,attributes,appendTo) {\n\t\tvar element = document.createElementNS('http://www.w3.org/2000/svg',tag);\n\t\tattr(element,attributes);\n\t\tif (appendTo) {\n\t\t\tappendTo.appendChild(element);\n\t\t}\n\t\treturn element;\n\t}\n\t\n\t// Set attributes for an element\n\tfunction attr(element,attrs) {\n\t\tfor (var i in attrs) {\n\t\t\telement.setAttribute(i,attrs[i]);\n\t\t}\n\t}\n\t\n\t// Rotate a cartesian point about given origin by X degrees\n\tfunction rotatePoint(point, angle, origin) {\n\t\tvar radians = angle * Math.PI/180;\n\t\tvar x = point[0]-origin[0];\n\t\tvar y = point[1]-origin[1];\n\t\tvar x1 = x*Math.cos(radians) - y*Math.sin(radians) + origin[0];\n\t\tvar y1 = x*Math.sin(radians) + y*Math.cos(radians) + origin[1];\n\t\treturn [x1,y1];\n\t}\n\t\n\t// Rotate an array of cartesian points about a given origin by X degrees\n\tfunction rotatePoints(points, angle, origin) {\n\t\treturn points.map(function(point) {\n\t\t\treturn rotatePoint(point, angle, origin);\n\t\t});\n\t}\n\t\n\t// Given an array of points, return an SVG path string representing the shape they define\n\tfunction pointsToPath(points) {\n\t\treturn points.map(function(point, iPoint) {\n\t\t\treturn (iPoint>0?'L':'M') + point[0] + ' ' + point[1];\n\t\t}).join(' ')+'Z';\n\t}\n\t\n\tfunction circleToPath(cx, cy, r) {\n\t\treturn [\n\t\t\t\"M\",cx,\",\",cy,\n\t\t\t\"m\",0-r,\",\",0,\n\t\t\t\"a\",r,\",\",r,0,1,\",\",0,r*2,\",\",0,\n\t\t\t\"a\",r,\",\",r,0,1,\",\",0,0-r*2,\",\",0,\n\t\t\t\"z\"\n\t\t].join(' ').replace(/\\s,\\s/g,\",\");\n\t}\n\t\n\tfunction donutPath(cx,cy,rOuter,rInner) {\n\t\treturn circleToPath(cx,cy,rOuter) + \" \" + circleToPath(cx,cy,rInner);\n\t}\n\t\n\t// Restrict a number to a min + max range\n\tfunction restrictToRange(val,min,max) {\n\t\tif (val < min) return min;\n\t\tif (val > max) return max;\n\t\treturn val;\n\t}\n\t\n\t// Round a number to the nearest 0.5\n\tfunction roundHalf(num) {\n\t\treturn Math.round(num*2)/2;\n\t}\n\t\n\tfunction setClass(el, className, state) {\n\t\tel.classList[state ? 'add' : 'remove'](className);\n\t}\n\t\n\t/*\n\t * The \"MEAT\"\n\t */\n\n\treturn function(targetElement, options) {\n\t\tvar self = this;\n\t\t\n\t\t/*\n\t\t * Options\n\t\t */\n\t\toptions = options || {};\n\t\toptions = {\n\t\t\tdiameter: options.diameter || 400,\n\t\t\tminValue: options.minValue || 10, // Minimum value for target temperature\n\t\t\tmaxValue: options.maxValue || 30, // Maximum value for target temperature\n\t\t\tnumTicks: options.numTicks || 200, // Number of tick lines to display around the dial\n\t\t\tonSetTargetTemperature: options.onSetTargetTemperature || function() {}, // Function called when new target temperature set by the dial\n\t\t};\n\t\t\n\t\t/*\n\t\t * Properties - calculated from options in many cases\n\t\t */\n\t\tvar properties = {\n\t\t\ttickDegrees: 300, // Degrees of the dial that should be covered in tick lines\n\t\t\trangeValue: options.maxValue - options.minValue,\n\t\t\tradius: options.diameter/2,\n\t\t\tticksOuterRadius: options.diameter / 30,\n\t\t\tticksInnerRadius: options.diameter / 8,\n\t\t\thvac_states: ['off', 'heating', 'cooling'],\n\t\t\tdragLockAxisDistance: 15,\n\t\t}\n\t\tproperties.lblAmbientPosition = [properties.radius, properties.ticksOuterRadius-(properties.ticksOuterRadius-properties.ticksInnerRadius)/2]\n\t\tproperties.offsetDegrees = 180-(360-properties.tickDegrees)/2;\n\t\t\n\t\t/*\n\t\t * Object state\n\t\t */\n\t\tvar state = {\n\t\t\ttarget_temperature: options.minValue,\n\t\t\tambient_temperature: options.minValue,\n\t\t\thvac_state: properties.hvac_states[0],\n\t\t\thas_leaf: false,\n\t\t\taway: false\n\t\t};\n\t\t\n\t\t/*\n\t\t * Property getter / setters\n\t\t */\n\t\tObject.defineProperty(this,'target_temperature',{\n\t\t\tget: function() {\n\t\t\t\treturn state.target_temperature;\n\t\t\t},\n\t\t\tset: function(val) {\n\t\t\t\tstate.target_temperature = restrictTargetTemperature(+val);\n\t\t\t\trender();\n\t\t\t}\n\t\t});\n\t\tObject.defineProperty(this,'ambient_temperature',{\n\t\t\tget: function() {\n\t\t\t\treturn state.ambient_temperature;\n\t\t\t},\n\t\t\tset: function(val) {\n\t\t\t\tstate.ambient_temperature = roundHalf(+val);\n\t\t\t\trender();\n\t\t\t}\n\t\t});\n\t\tObject.defineProperty(this,'hvac_state',{\n\t\t\tget: function() {\n\t\t\t\treturn state.hvac_state;\n\t\t\t},\n\t\t\tset: function(val) {\n\t\t\t\tif (properties.hvac_states.indexOf(val)>=0) {\n\t\t\t\t\tstate.hvac_state = val;\n\t\t\t\t\trender();\n\t\t\t\t}\n\t\t\t}\n\t\t});\n\t\tfunction str2bool(strvalue){\n          return (strvalue && typeof strvalue == 'string') ? (strvalue.toLowerCase() == 'true') : (strvalue == true);\n        }\n\t\tObject.defineProperty(this,'has_leaf',{\n\t\t\tget: function() {\n\t\t\t\treturn state.has_leaf;\n\t\t\t},\n\t\t\tset: function(val) {\n\t\t\t\tstate.has_leaf = !!str2bool(val);\n\t\t\t\trender();\n\t\t\t}\n\t\t});\n\t\tObject.defineProperty(this,'away',{\n\t\t\tget: function() {\n\t\t\t\treturn state.away;\n\t\t\t},\n\t\t\tset: function(val) {\n\t\t\t\tstate.away = !!str2bool(val);\n\t\t\t\trender();\n\t\t\t}\n\t\t});\n\t\t\n\t\t/*\n\t\t * SVG\n\t\t */\n\t\tvar svg = createSVGElement('svg',{\n\t\t\twidth: '100%', //options.diameter+'px',\n\t\t\theight: '100%', //options.diameter+'px',\n\t\t\tviewBox: '0 0 '+options.diameter+' '+options.diameter,\n\t\t\tclass: 'dial'\n\t\t},targetElement);\n\t\t// CIRCULAR DIAL\n\t\tvar circle = createSVGElement('circle',{\n\t\t\tcx: properties.radius,\n\t\t\tcy: properties.radius,\n\t\t\tr: properties.radius,\n\t\t\tclass: 'dial__shape'\n\t\t},svg);\n\t\t// EDITABLE INDICATOR\n\t\tvar editCircle = createSVGElement('path',{\n\t\t\td: donutPath(properties.radius,properties.radius,properties.radius-4,properties.radius-8),\n\t\t\tclass: 'dial__editableIndicator',\n\t\t},svg);\n\t\t\n\t\t/*\n\t\t * Ticks\n\t\t */\n\t\tvar ticks = createSVGElement('g',{\n\t\t\tclass: 'dial__ticks'\t\n\t\t},svg);\n\t\tvar tickPoints = [\n\t\t\t[properties.radius-1, properties.ticksOuterRadius],\n\t\t\t[properties.radius+1, properties.ticksOuterRadius],\n\t\t\t[properties.radius+1, properties.ticksInnerRadius],\n\t\t\t[properties.radius-1, properties.ticksInnerRadius]\n\t\t];\n\t\tvar tickPointsLarge = [\n\t\t\t[properties.radius-1.5, properties.ticksOuterRadius],\n\t\t\t[properties.radius+1.5, properties.ticksOuterRadius],\n\t\t\t[properties.radius+1.5, properties.ticksInnerRadius+20],\n\t\t\t[properties.radius-1.5, properties.ticksInnerRadius+20]\n\t\t];\n\t\tvar theta = properties.tickDegrees/options.numTicks;\n\t\tvar tickArray = [];\n\t\tfor (var iTick=0; iTick<options.numTicks; iTick++) {\n\t\t\ttickArray.push(createSVGElement('path',{d:pointsToPath(tickPoints)},ticks));\n\t\t};\n\t\t\n\t\t/*\n\t\t * Labels\n\t\t */\n\t\tvar lblTarget = createSVGElement('text',{\n\t\t\tx: properties.radius,\n\t\t\ty: properties.radius,\n\t\t\tclass: 'dial__lbl dial__lbl--target'\n\t\t},svg);\n\t\tvar lblTarget_text = document.createTextNode('');\n\t\tlblTarget.appendChild(lblTarget_text);\n\t\t//\n\t\tvar lblTargetHalf = createSVGElement('text',{\n\t\t\tx: properties.radius + properties.radius/2.5,\n\t\t\ty: properties.radius - properties.radius/8,\n\t\t\tclass: 'dial__lbl dial__lbl--target--half'\n\t\t},svg);\n\t\tvar lblTargetHalf_text = document.createTextNode('5');\n\t\tlblTargetHalf.appendChild(lblTargetHalf_text);\n\t\t//\n\t\tvar lblAmbient = createSVGElement('text',{\n\t\t\tclass: 'dial__lbl dial__lbl--ambient'\n\t\t},svg);\n\t\tvar lblAmbient_text = document.createTextNode('');\n\t\tlblAmbient.appendChild(lblAmbient_text);\n\t\t//\n\t\tvar lblAway = createSVGElement('text',{\n\t\t\tx: properties.radius,\n\t\t\ty: properties.radius,\n\t\t\tclass: 'dial__lbl dial__lbl--away'\n\t\t},svg);\n\t\tvar lblAway_text = document.createTextNode('AWAY');\n\t\tlblAway.appendChild(lblAway_text);\n\t\t//\n\t\tvar icoLeaf = createSVGElement('path',{\n\t\t\tclass: 'dial__ico__leaf'\n\t\t},svg);\n\t\t\n\t\t/*\n\t\t * LEAF\n\t\t */\n\t\tvar leafScale = properties.radius/5/100;\n\t\tvar leafDef = [\"M\", 3, 84, \"c\", 24, 17, 51, 18, 73, -6, \"C\", 100, 52, 100, 22, 100, 4, \"c\", -13, 15, -37, 9, -70, 19, \"C\", 4, 32, 0, 63, 0, 76, \"c\", 6, -7, 18, -17, 33, -23, 24, -9, 34, -9, 48, -20, -9, 10, -20, 16, -43, 24, \"C\", 22, 63, 8, 78, 3, 84, \"z\"].map(function(x) {\n\t\t\treturn isNaN(x) ? x : x*leafScale;\n\t\t}).join(' ');\n\t\tvar translate = [properties.radius-(leafScale*100*0.5),properties.radius*1.5]\n\t\tvar icoLeaf = createSVGElement('path',{\n\t\t\tclass: 'dial__ico__leaf',\n\t\t\td: leafDef,\n\t\t\ttransform: 'translate('+translate[0]+','+translate[1]+')'\n\t\t},svg);\n\t\t\t\n\t\t/*\n\t\t * RENDER\n\t\t */\n\t\tfunction render() {\n\t\t\trenderAway();\n\t\t\trenderHvacState();\n\t\t\trenderTicks();\n\t\t\trenderTargetTemperature();\n\t\t\trenderAmbientTemperature();\n\t\t\trenderLeaf();\n\t\t}\n\t\trender();\n\n\t\t/*\n\t\t * RENDER - ticks\n\t\t */\n\t\tfunction renderTicks() {\n\t\t\tvar vMin, vMax;\n\t\t\tif (self.away) {\n\t\t\t\tvMin = self.ambient_temperature;\n\t\t\t\tvMax = vMin;\n\t\t\t} else {\n\t\t\t\tvMin = Math.min(self.ambient_temperature, self.target_temperature);\n\t\t\t\tvMax = Math.max(self.ambient_temperature, self.target_temperature);\n\t\t\t}\n\t\t\tvar min = restrictToRange(Math.round((vMin-options.minValue)/properties.rangeValue * options.numTicks),0,options.numTicks-1);\n\t\t\tvar max = restrictToRange(Math.round((vMax-options.minValue)/properties.rangeValue * options.numTicks),0,options.numTicks-1);\n\t\t\t//\n\t\t\ttickArray.forEach(function(tick,iTick) {\n\t\t\t\tvar isLarge = iTick==min || iTick==max;\n\t\t\t\tvar isActive = iTick >= min && iTick <= max;\n\t\t\t\tattr(tick,{\n\t\t\t\t\td: pointsToPath(rotatePoints(isLarge ? tickPointsLarge: tickPoints,iTick*theta-properties.offsetDegrees,[properties.radius, properties.radius])),\n\t\t\t\t\tclass: isActive ? 'active' : ''\n\t\t\t\t});\n\t\t\t});\n\t\t}\n\t\n\t\t/*\n\t\t * RENDER - ambient temperature\n\t\t */\n\t\tfunction renderAmbientTemperature() {\n\t\t\tlblAmbient_text.nodeValue = Math.floor(self.ambient_temperature);\n\t\t\tif (self.ambient_temperature%1!=0) {\n\t\t\t\tlblAmbient_text.nodeValue += '⁵';\n\t\t\t}\n\t\t\tvar peggedValue = restrictToRange(self.ambient_temperature, options.minValue, options.maxValue);\n\t\t\tdegs = properties.tickDegrees * (peggedValue-options.minValue)/properties.rangeValue - properties.offsetDegrees;\n\t\t\tif (peggedValue > self.target_temperature) {\n\t\t\t\tdegs += 8;\n\t\t\t} else {\n\t\t\t\tdegs -= 8;\n\t\t\t}\n\t\t\tvar pos = rotatePoint(properties.lblAmbientPosition,degs,[properties.radius, properties.radius]);\n\t\t\tattr(lblAmbient,{\n\t\t\t\tx: pos[0],\n\t\t\t\ty: pos[1]\n\t\t\t});\n\t\t}\n\n\t\t/*\n\t\t * RENDER - target temperature\n\t\t */\n\t\tfunction renderTargetTemperature() {\n\t\t\tlblTarget_text.nodeValue = Math.floor(self.target_temperature);\n\t\t\tsetClass(lblTargetHalf,'shown',self.target_temperature%1!=0);\n\t\t}\n\t\t\n\t\t/*\n\t\t * RENDER - leaf\n\t\t */\n\t\tfunction renderLeaf() {\n\t\t\tsetClass(svg,'has-leaf',self.has_leaf);\n\t\t}\n\t\t\n\t\t/*\n\t\t * RENDER - HVAC state\n\t\t */\n\t\tfunction renderHvacState() {\n\t\t\tArray.prototype.slice.call(svg.classList).forEach(function(c) {\n\t\t\t\tif (c.match(/^dial--state--/)) {\n\t\t\t\t\tsvg.classList.remove(c);\n\t\t\t\t};\n\t\t\t});\n\t\t\tsvg.classList.add('dial--state--'+self.hvac_state);\n\t\t}\n\t\t\n\t\t/*\n\t\t * RENDER - away\n\t\t */\n\t\tfunction renderAway() {\n\t\t\tsvg.classList[self.away ? 'add' : 'remove']('away');\n\t\t}\n\t\t\n\t\t/*\n\t\t * Drag to control\n\t\t */\n\t\tvar _drag = {\n\t\t\tinProgress: false,\n\t\t\tstartPoint: null,\n\t\t\tstartTemperature: 0,\n\t\t\tlockAxis: undefined\n\t\t};\n\t\t\n\t\tfunction eventPosition(ev) {\n\t\t\tif (ev.targetTouches && ev.targetTouches.length) {\n\t\t\t\treturn [ev.targetTouches[0].clientX, ev.targetTouches[0].clientY];\n\t\t\t} else {\n\t\t\t\treturn [ev.x, ev.y];\n\t\t\t};\n\t\t}\n\t\t\n\t\tvar startDelay;\n\t\tfunction dragStart(ev) {\n\t\t\tstartDelay = setTimeout(function() {\n\t\t\t\tsetClass(svg, 'dial--edit', true);\n\t\t\t\t_drag.inProgress = true;\n\t\t\t\t_drag.startPoint = eventPosition(ev);\n\t\t\t\t_drag.startTemperature = self.target_temperature || options.minValue;\n\t\t\t\t_drag.lockAxis = undefined;\n\t\t\t},1000);\n\t\t};\n\t\t\n\t\tfunction dragEnd (ev) {\n\t\t\tclearTimeout(startDelay);\n\t\t\tsetClass(svg, 'dial--edit', false);\n\t\t\tif (!_drag.inProgress) return;\n\t\t\t_drag.inProgress = false;\n\t\t\tif (self.target_temperature != _drag.startTemperature) {\n\t\t\t\tif (typeof options.onSetTargetTemperature == 'function') {\n\t\t\t\t\toptions.onSetTargetTemperature(self.target_temperature);\n\t\t\t\t};\n\t\t\t};\n\t\t};\n\t\t\n\t\tfunction dragMove(ev) {\n\t\t\tev.preventDefault();\n\t\t\tif (!_drag.inProgress) return;\n\t\t\tvar evPos = eventPosition(ev);\n\t\t\tvar dy = _drag.startPoint[1]-evPos[1];\n\t\t\tvar dx = evPos[0] - _drag.startPoint[0];\n\t\t\tvar dxy;\n\t\t\tif (_drag.lockAxis == 'x') {\n\t\t\t\tdxy = dx;\n\t\t\t} else if (_drag.lockAxis == 'y') {\n\t\t\t\tdxy = dy;\n\t\t\t} else if (Math.abs(dy) > properties.dragLockAxisDistance) {\n\t\t\t\t_drag.lockAxis = 'y';\n\t\t\t\tdxy = dy;\n\t\t\t} else if (Math.abs(dx) > properties.dragLockAxisDistance) {\n\t\t\t\t_drag.lockAxis = 'x';\n\t\t\t\tdxy = dx;\n\t\t\t} else {\n\t\t\t\tdxy = (Math.abs(dy) > Math.abs(dx)) ? dy : dx;\n\t\t\t};\n\t\t\tvar dValue = (dxy*getSizeRatio())/(options.diameter)*properties.rangeValue;\n\t\t\tself.target_temperature = roundHalf(_drag.startTemperature+dValue);\n\t\t}\n\t\t\n\t\tsvg.addEventListener('mousedown',dragStart);\n\t\tsvg.addEventListener('touchstart',dragStart);\n\t\t\n\t\tsvg.addEventListener('mouseup',dragEnd);\n\t\tsvg.addEventListener('mouseleave',dragEnd);\n\t\tsvg.addEventListener('touchend',dragEnd);\n\t\t\n\t\tsvg.addEventListener('mousemove',dragMove);\n\t\tsvg.addEventListener('touchmove',dragMove);\n\t\t//\n\t\t\n\t\t/*\n\t\t * Helper functions\n\t\t */\n\t\tfunction restrictTargetTemperature(t) {\n\t\t\treturn restrictToRange(roundHalf(t),options.minValue,options.maxValue);\n\t\t}\n\t\t\n\t\tfunction angle(point) {\n\t\t\tvar dx = point[0] - properties.radius;\n\t\t\tvar dy = point[1] - properties.radius;\n\t\t\tvar theta = Math.atan(dx/dy) / (Math.PI/180);\n\t\t\tif (point[0]>=properties.radius && point[1] < properties.radius) {\n\t\t\t\ttheta = 90-theta - 90;\n\t\t\t} else if (point[0]>=properties.radius && point[1] >= properties.radius) {\n\t\t\t\ttheta = 90-theta + 90;\n\t\t\t} else if (point[0]<properties.radius && point[1] >= properties.radius) {\n\t\t\t\ttheta = 90-theta + 90;\n\t\t\t} else if (point[0]<properties.radius && point[1] < properties.radius) {\n\t\t\t\ttheta = 90-theta+270;\n\t\t\t}\n\t\t\treturn theta;\n\t\t};\n\t\t\n\t\tfunction getSizeRatio() {\n\t\t\treturn options.diameter / targetElement.clientWidth;\n\t\t}\n\t\t\n\t};\n})();\n\n/* ==== */\nvar initializing = true;\n\n(function(scope) {\n    var nest = new thermostatDial(document.getElementById('thermostat'),{\n    \tonSetTargetTemperature: function(v) {\n    \t    var p = {\n    \t        \"ambient_temperature\":nest.ambient_temperature,\n    \t        \"target_temperature\":v,\n    \t        \"hvac_state\":nest.hvac_state,\n    \t        \"has_leaf\": nest.has_leaf,\n    \t        \"away\":nest.away\n    \t    };\n    \t\tscope.send({topic: \"target_temperature\", payload: p});\n    \t}\n    });\n    \n    scope.$watch('msg', function(data) {\n        if (initializing) {\n            initializing = false;\n            } else {\n            nest.ambient_temperature = data.payload.ambient_temperature || 0;\n            nest.target_temperature = data.payload.target_temperature || 0;\n            nest.hvac_state = data.payload.hvac_state || \"off\";\n            nest.has_leaf = data.payload.has_leaf || false;\n            nest.away = data.payload.away || false;\n        }\n        \n    });\n})(scope);\n\n</script>","storeOutMessages":true,"fwdInMessages":false,"templateScope":"local","x":790,"y":140,"wires":[["3cb0268a.c5fcca","50c7f400.4fee8c"]]},{"id":"eafe16b3.8f69b8","type":"function","z":"d862700a.a9435","name":"ambient_temperature","func":"msg.topic = 'ambient_temperature';\nglobal.set(\"nest1_ambient_temperature\", msg.payload);\nreturn msg;","outputs":1,"noerr":0,"x":440,"y":140,"wires":[["2976bfe0.29d5c"]]},{"id":"4a13f425.a2797c","type":"function","z":"d862700a.a9435","name":"target_temperature","func":"msg.topic = 'target_temperature';\nglobal.set(\"nest1_target_temperature\",msg.payload);\nreturn msg;","outputs":1,"noerr":0,"x":430,"y":180,"wires":[["2976bfe0.29d5c"]]},{"id":"489645d1.af57fc","type":"function","z":"d862700a.a9435","name":"hvac_state","func":"msg.topic = \"hvac_state\";\nglobal.set(\"nest1_hvac_state\",msg.payload);\nreturn msg;","outputs":1,"noerr":0,"x":410,"y":220,"wires":[["2976bfe0.29d5c"]]},{"id":"5fd020bb.4b501","type":"function","z":"d862700a.a9435","name":"has_leaf","func":"msg.topic = \"has_leaf\";\nglobal.set(\"nest1_has_leaf\", msg.payload);\nreturn msg;","outputs":1,"noerr":0,"x":400,"y":260,"wires":[["2976bfe0.29d5c"]]},{"id":"3eeeba54.12ba56","type":"function","z":"d862700a.a9435","name":"away","func":"msg.topic = \"away\";\nglobal.set(\"nest1_away\", msg.payload);\nreturn msg;","outputs":1,"noerr":0,"x":390,"y":300,"wires":[["2976bfe0.29d5c"]]},{"id":"93c327e6.675808","type":"inject","z":"d862700a.a9435","name":"","repeat":"","crontab":"","once":false,"onceDelay":"","topic":"has_leaf","payload":"true","payloadType":"bool","x":130,"y":340,"wires":[["5fd020bb.4b501"]]},{"id":"4e4237c7.91b748","type":"inject","z":"d862700a.a9435","name":"","repeat":"","crontab":"","once":false,"topic":"has_leaf","payload":"false","payloadType":"bool","x":130,"y":380,"wires":[["5fd020bb.4b501"]]},{"id":"77cc7555.224acc","type":"inject","z":"d862700a.a9435","name":"","repeat":"","crontab":"","once":false,"onceDelay":"","topic":"away","payload":"true","payloadType":"str","x":120,"y":420,"wires":[["3eeeba54.12ba56"]]},{"id":"6114d1b.e7c993","type":"inject","z":"d862700a.a9435","name":"","repeat":"","crontab":"","once":false,"topic":"away","payload":"false","payloadType":"bool","x":120,"y":460,"wires":[["3eeeba54.12ba56"]]},{"id":"a4ee3cde.db88f","type":"inject","z":"d862700a.a9435","name":"","repeat":"","crontab":"","once":false,"topic":"hvac_state","payload":"off","payloadType":"str","x":130,"y":220,"wires":[["489645d1.af57fc"]]},{"id":"85fd556.398baa8","type":"inject","z":"d862700a.a9435","name":"","repeat":"","crontab":"","once":false,"topic":"hvac_state","payload":"heating","payloadType":"str","x":150,"y":260,"wires":[["489645d1.af57fc"]]},{"id":"1f5f7f68.be21e1","type":"inject","z":"d862700a.a9435","name":"","repeat":"","crontab":"","once":false,"topic":"hvac_state","payload":"cooling","payloadType":"str","x":150,"y":300,"wires":[["489645d1.af57fc"]]},{"id":"2034d66f.48bada","type":"inject","z":"d862700a.a9435","name":"","repeat":"","crontab":"","once":false,"onceDelay":"","topic":"ambient_temperature","payload":"21.6","payloadType":"str","x":170,"y":140,"wires":[["eafe16b3.8f69b8"]]},{"id":"390f760d.9071fa","type":"inject","z":"d862700a.a9435","name":"","repeat":"","crontab":"","once":false,"onceDelay":"","topic":"target_temperature","payload":"18","payloadType":"str","x":160,"y":180,"wires":[["4a13f425.a2797c"]]},{"id":"9618891e.b03348","type":"debug","z":"d862700a.a9435","name":"To your target_temperature MQTT topic","active":false,"tosidebar":true,"console":false,"tostatus":false,"complete":"payload","x":1300,"y":140,"wires":[]},{"id":"50c7f400.4fee8c","type":"debug","z":"d862700a.a9435","name":"","active":true,"tosidebar":true,"console":false,"tostatus":false,"complete":"true","x":930,"y":200,"wires":[]},{"id":"2976bfe0.29d5c","type":"function","z":"d862700a.a9435","name":"Data","func":"if (msg.topic == \"target_temperature\") {\n    global.set(\"nest1_target_temperature\",msg.payload);\n}\nmsg.topic = \"update\";\nvar data = {\n    'ambient_temperature': global.get(\"nest1_ambient_temperature\") || 20,\n    'target_temperature': global.get(\"nest1_target_temperature\") || 21,\n    'hvac_state': global.get(\"nest1_hvac_state\") || 'off',\n    'has_leaf': global.get(\"nest1_has_leaf\") || 'false',\n    'away': global.get(\"nest1_away\") || 'false'\n}\nmsg.payload = data;\nreturn msg;","outputs":1,"noerr":0,"x":650,"y":140,"wires":[["b29b8821.850688"]]},{"id":"3cb0268a.c5fcca","type":"function","z":"d862700a.a9435","name":"New setpoint from UI","func":"if (msg.topic == \"target_temperature\") {\n    global.set(\"nest1_target_temperature\",msg.payload.target_temperature);\n    return msg;\n}\n","outputs":1,"noerr":0,"x":980,"y":140,"wires":[["9618891e.b03348"]]},{"id":"99f40918.cb4138","type":"inject","z":"d862700a.a9435","name":"Load values on node-red startup","repeat":"","crontab":"","once":true,"onceDelay":0.1,"topic":"","payload":"","payloadType":"date","x":410,"y":100,"wires":[["2976bfe0.29d5c"]]},{"id":"76ac5dbd.8ea9c4","type":"ui_button","z":"d087fa29.08fdc8","name":"","group":"9a6c950b.59f2e8","order":3,"width":0,"height":0,"passthru":false,"label":"Refresh","tooltip":"","color":"","bgcolor":"","icon":"","payload":"","payloadType":"str","topic":"","x":90,"y":500,"wires":[["41e00e3.01f5ff"]]},{"id":"b3236385.41e87","type":"mqtt in","z":"9c834b39.564c48","name":"","topic":"HotBinTemp/value1","qos":"0","datatype":"auto","broker":"e2eaf260.27fa1","x":110,"y":40,"wires":[["69cc0d3.38729f4"]]},{"id":"69cc0d3.38729f4","type":"ui_chart","z":"9c834b39.564c48","name":"Hot Bin Temp Chart","group":"9faad522.25f398","order":6,"width":"9","height":"3","label":"Hot Bin Temp {{msg.payload}}&#176;C","chartType":"line","legend":"false","xformat":"auto","interpolate":"linear","nodata":"","dot":false,"ymin":"","ymax":"","removeOlder":"2","removeOlderPoints":"","removeOlderUnit":"86400","cutout":0,"useOneColor":false,"useUTC":false,"colors":["#5ad873","#13ec2c","#ff7f0e","#2ca02c","#98df8a","#d62728","#ff9896","#9467bd","#c5b0d5"],"outputs":1,"x":770,"y":40,"wires":[[]]},{"id":"2247f270.a8a36e","type":"mqtt in","z":"9c834b39.564c48","name":"","topic":"Current/watts","qos":"0","datatype":"auto","broker":"e2eaf260.27fa1","x":90,"y":220,"wires":[["f063d2db.04b9b"]]},{"id":"f063d2db.04b9b","type":"ui_chart","z":"9c834b39.564c48","name":"Watt Chart","group":"9faad522.25f398","order":7,"width":"18","height":"4","label":"Using {{msg.payload}} Watts","chartType":"line","legend":"false","xformat":"HH:mm:ss","interpolate":"linear","nodata":"","dot":false,"ymin":"","ymax":"","removeOlder":"12","removeOlderPoints":"","removeOlderUnit":"3600","cutout":0,"useOneColor":false,"colors":["#8080ff","#aec7e8","#ff7f0e","#2ca02c","#98df8a","#d62728","#ff9896","#9467bd","#c5b0d5"],"outputs":1,"x":750,"y":220,"wires":[[]]},{"id":"87e288fe.696168","type":"inject","z":"9c834b39.564c48","name":"","repeat":"","crontab":"","once":false,"onceDelay":0.1,"topic":"HotBinTemp/value","payload":"[]","payloadType":"json","x":550,"y":60,"wires":[["69cc0d3.38729f4"]]},{"id":"3169839d.93effc","type":"function","z":"9c834b39.564c48","name":"FIlter zero","func":"if ( msg.payload <= 0 )\n    return null;\nreturn msg;","outputs":1,"noerr":0,"initialize":"","finalize":"","x":510,"y":160,"wires":[["55d86634.5b3168"]]}]